Workbook

Sheet En plazo
A1: Nueva | B1: Fecha límite | C1: Días restantes | D1: Presupuesto base sin IVA | E1: Valor estimado | F1: Comunidad | G1: Provincia | H1: Municipio | I1: Órgano de contratación | J1: Objeto | K1: Expediente | L1: Procedimiento | M1: Plazo de ejecución (meses) | N1: Clasificación exigida | O1: Juicio de valor | P1: Criterios de adjudicación | Q1: Garantías | R1: Revisión de precios | S1: Nº lotes | T1: CPV | U1: PCAP | V1: PPT | W1: Ficha PLACSP | X1: Primera detección | Y1: Cambios
B2: 46321.375 | C2: =IF(B2="","",INT(B2)-TODAY()) | D2: 889866.1 | E2: 1067839.3 | F2: Comunitat Valenciana | G2: Alicante | H2: Alicante | I2: Mercados Centrales De Abastecimiento de Alicante S.A. | J2: Sustitución de las cubiertas de fibrocemento de la nave III de Mercalicante | K2: 21/2026EXPL | L2: Abierto simplificado | M2: 10 | O2: 0.25 | P2: Plan de obra 5 (JV) | Experiencia del jefe y del encargado de obra 10 | Ampliación del plazo de garantía 5 | Memoria y estudio de obra 20 (JV) | Oferta económica 54 | Mantenimiento de la cubierta y líneas de vida 6 | Q2: complementaria 5%; definitiva 5% | T2: 45000000; 45421160; 45261220; 45262660; 45261420 | U2: PCAP | V2: PPT | W2: Ver | X2: 46310
B3: 46321.542 | C3: =IF(B3="","",INT(B3)-TODAY()) | D3: 3837538.7 | E3: 4221292.6 | F3: Andalucía | G3: Sevilla | I3: Gerencia de Sevilla Activa SAU | J3: Terminación de 50 Viviendas Protegidas | K3: A41420191-2026/000082-PaA | L3: Abierto | M3: 12 | N3: C*-5; G*-5; G6-4; C4-4 | O3: 0.3 | P3: memoria técnica [1] 30 (JV) | ampliación del plazo de garantía de la obra sobre el mínimo de un año [3] 15 | visita guiada [2] 15 | Aspecto Económico (precio) [1] 40 | T3: 45211000 | U3: PCAP | V3: PPT | W3: Ver | X3: 46310
B4: 46321.583 | C4: =IF(B4="","",INT(B4)-TODAY()) | D4: 585223.15 | E4: 585223.15 | F4: Comunitat Valenciana | G4: Valencia | I4: Presidencia de la Entidad Valenciana de Vivienda y Suelo | J4: Obras de Reparación y Refuerzo Estructural e Intervenciones puntuales en Fachadas y Cubiertas, así como Obras de Reparación y Refuerzo Estructural e Intervenciones puntuales en el interior de los edificios de la Manzana D del Grupo de Viviendas de Promoción Pública 030001 Miguel Hernández de Alicante. | K4: CMAYOR/2026/EVHA0/0011 | L4: Abierto simplificado | M4: 4 | N4: C4-3; C*-4 | O4: 0.2 | P4: CALIDAD 20 (JV) | Oferta económica 80 | Q4: definitiva 5% | T4: 45200000 | U4: PCAP | V4: PPT | W4: Ver | X4: 46317
B5: 46321.583 | C5: =IF(B5="","",INT(B5)-TODAY()) | D5: 792000 | E5: 1742400 | F5: Comunitat Valenciana | G5: Valencia | I5: Presidencia de la Entidad Valenciana de Vivienda y Suelo | J5: Mantenimiento correctivo (incluyendo la gestión integral de reclamaciones) de los inmuebles que componen el patrimonio público de viviendas de la Generalitat en la provincia de Castellón para los ejercicios 2027/2028. | K5: CMAYOR/2026/EVHA0/0012 | L5: Abierto | M5: 24 | N5: I6-1; C4-2; J4-1; C9-2 | O5: 0.4 | P5: Seguridad y Salud 5 (JV) | Control de calidad 5 (JV) | Propuesta organizativa 10 (JV) | Oferta económica 60 | Propuesta metodológica 10 (JV) | Análisis Plazos estimados y Base de Precios 10 (JV) | Q5: definitiva 5% | T5: 45200000; 71000000 | U5: PCAP | W5: Ver | X5: 46317
B6: 46321.792 | C6: =IF(B6="","",INT(B6)-TODAY()) | D6: 1650496 | E6: 1650496 | F6: Andalucía | G6: Málaga | I6: Instituto de Turismo de España (TURESPAÑA) | J6: Contrato para la ejecución de obras de la Fase II de las obras para la protección y consolidación del frente de acantilado del parador de turismo de Nerja (Málaga) | K6: 020026C00098 | L6: Abierto simplificado | M6: 10 | O6: 0 | P6: OFERTA ECONÓMICA 65 | OTROS CRITERIOS CUANTIFICABLES AUTOMATICAMENTE 35 | Q6: complementaria 5%; definitiva 5% | T6: 45200000 | U6: PCAP | V6: PPT | W6: Ver | X6: 46310
B7: 46321.999 | C7: =IF(B7="","",INT(B7)-TODAY()) | D7: 636363.64 | E7: 636363.64 | F7: Andalucía | G7: Huelva | I7: Junta de Gobierno del Ayuntamiento de Almonte | J7: ejecución de obras del proyecto de ejecución para la rehabilitación energética del edificio "hacienda santa maría" -proyectos Miteco- derivadas de proyecto subvencionado por el ministerio para la transición ecológica y el reto demográfico en aplicación del Real decreto 842/2024, de 27 de agosto, | K7: 12054/2026 | L7: Abierto simplificado | M7: 10 | N7: C*-3 | O7: 0.25 | P7: Procedencia de materiales y proveedores 4 (JV) | Compromiso de reducción del plazo de ejecución de la obra 25 | Recursos: personal, maquinaria y medios auxiliares 7 (JV) | Mejoras sociales de inserción 10 | Propuesta Plan de Obra 5 (JV) | Organización de los trabajos 5 (JV) | Ampliación de garantía 10 | Mejoras ambientales y/o de accesibilidad 20 | Propuesta del Plan de Aseguramiento de la Calidad 4 (JV) | Medidas medioambientales 10 | Q7: definitiva 5% | T7: 45200000 | U7: PCAP | V7: PPT | W7: Ver | X7: 46310
B8: 46321.999 | C8: =IF(B8="","",INT(B8)-TODAY()) | D8: 1025843.2 | E8: 1025843.2 | F8: Andalucía | G8: Málaga | H8: Alhaurín el Grande | I8: Alcaldía del Ayuntamiento de Alhaurín el Grande | J8: Proyecto de obras de renaturalización de las Avenidas Blas Infante y Libertad. Tramo 4 | K8: 25734/2026 BLAS INFANTE Y LIBERTAD | L8: Abierto simplificado | M8: 14 | O8: 0.1 | P8: Proposición económica 80 | Memoria constructiva y programa de trabajo 4 (JV) | Medidas para reducir el impacto Ambiental 2 (JV) | Medidas para reducir el impacto urbano de la obra 4 (JV) | ampliación en el plazo de garantía 10 | Q8: definitiva 5% | T8: 45223210; 45262520; 45233140; 45262210; 45112000; 45232100 | U8: PCAP | V8: PPT | W8: Ver | X8: 46310
B9: 46321.999 | C9: =IF(B9="","",INT(B9)-TODAY()) | D9: 4198877.4 | E9: 4198877.4 | F9: Comunitat Valenciana | G9: Alicante | I9: Consejo de Administración de Promociones e Iniciativas Municipales de Elche, S.A. (PIMESA) | J9: Obras de Construcción de un Edificio de 45 viviendas protegidas (VPNC), local, sótano para 44 aparcamientos y urbanización interior en la calle Obispo Cubero, nº2, Parcela nº5 del PRIM, Barrio San Antón de Elche. | K9: 2026/A/003 | L9: Abierto | M9: 24 | N9: C*-4 | O9: 0.25 | P9: Criterios evaluables mediante juicio de valor. 25 (JV) | Criterio evaluable de forma automática. Otros criterios 15 | Criterios evaluables de forma automática. Oferta Económica 60 | Q9: definitiva 5% | T9: 45211340 | U9: PCAP | W9: Ver | X9: 46311
B10: 46321.999 | C10: =IF(B10="","",INT(B10)-TODAY()) | D10: 725142.59 | E10: 725142.59 | F10: Andalucía | G10: Almería | I10: Junta de Gobierno de la Diputación Provincial de Almería | J10: Consolidacióin Primaria Cortijo Del Fraile 1PGM2026 | K10: 2026/D31000/006-013/00029 | L10: Abierto simplificado | M10: 10 | O10: 0.25 | P10: Oferta Técnica 25 (JV) | Precio 75 | Q10: complementaria 5%; definitiva 5% | T10: 45212350 | U10: PCAP | V10: PPT | W10: Ver | X10: 46317
B11: 46322.999 | C11: =IF(B11="","",INT(B11)-TODAY()) | D11: 1408264.5 | E11: 1408264.5 | F11: Andalucía | G11: Almería | I11: Junta de Gobierno de la Diputación Provincial de Almería | J11: Obras De Urbanización Para Un Complejo Deportivo. Vera 72PPOS24-27BI | K11: 2026/D31000/006-013/00078 | L11: Abierto simplificado | M11: 12.2 | N11: G6-4 | O11: 0.25 | P11: Oferta técnica 25 (JV) | Precio 75 | Q11: definitiva 5%; complementaria 5% | T11: 45233200 | U11: PCAP | V11: PPT | W11: Ver | X11: 46310
B12: 46322.999 | C12: =IF(B12="","",INT(B12)-TODAY()) | D12: 826446.28 | E12: 826446.28 | F12: Andalucía | G12: Almería | I12: Junta de Gobierno de la Diputación Provincial de Almería | J12: Rehabilitación Y Mejora De Edificios Municipales. Benahadux 19PPOS24-27BII | K12: 2026/D31000/006-013/00009 | L12: Abierto simplificado | M12: 15 | N12: C6-3; C4-3 | O12: 0.25 | P12: Oferta Técnica 25 (JV) | Precio 75 | Q12: complementaria 5%; definitiva 5% | T12: 45214000 | U12: PCAP | V12: PPT | W12: Ver | X12: 46310
B13: 46323.041 | C13: =IF(B13="","",INT(B13)-TODAY()) | D13: 547041.28 | E13: 547041.28 | F13: Andalucía | G13: Sevilla | H13: Sevilla | I13: Consejo de Administración de la Agencia de Régimen Especial Ciclo Integral Aguas del Retortillo | J13: PAS/OBRAS/007/2026 Obras construcción EDAR Natural Puerto de la Encina | K13: 1009/2026 | L13: Abierto simplificado | M13: 6 | N13: E1-3 | O13: 0 | P13: Calidad: Ampliación Garantía 6 | Calidad. Experiencia Jefe de Obras 10 | PRECIO 84 | Q13: definitiva 5% | T13: 45252100 | U13: PCAP | V13: PPT | W13: Ver | X13: 46310
B14: 46323.5 | C14: =IF(B14="","",INT(B14)-TODAY()) | D14: 794991.59 | E14: 794991.59 | F14: Andalucía | G14: Málaga | H14: Málaga | I14: Aena. Dirección del Aeropuerto de Málaga-Costa del Sol | J14: Ampliación Y Adecuación De Aseo 208 En El Aeropuerto De Málaga ¿ Costa Del Sol | K14: AGP-147/2026 | L14: Normas internas | M14: 14 | O14: 0 | P14: Precio 100 | T14: 45211310 | U14: PCAP | V14: PPT | W14: Ver | X14: 46310
B15: 46323.5 | C15: =IF(B15="","",INT(B15)-TODAY()) | D15: 653963.23 | E15: 653963.23 | F15: Comunitat Valenciana | G15: Alicante | H15: Almoradí | I15: Junta de Gobierno del Ayuntamiento de Almoradí | J15: Mejora de la accesibilidad y la escena urbana en el entorno del Teatro Cortés y Museo del Terremoto (Plan de Actuación Integrado PAI, cofinanciado con la Unión Europea - FEDER) | K15: 6981/2026 | L15: Abierto simplificado | M15: 5 | O15: 0.25 | P15: Proposición económica 75 | Memoria Técnica 25 (JV) | Q15: complementaria 5%; definitiva 5% | T15: 45233200; 45000000; 45111100; 45233140; 45233253; 45211360 | U15: PCAP | W15: Ver | X15: 46310
B16: 46323.999 | C16: =IF(B16="","",INT(B16)-TODAY()) | D16: 734951.31 | E16: 734951.31 | F16: Comunitat Valenciana | G16: Valencia | I16: Alcaldía del Ayuntamiento de Manises | J16: Reasfaltado de la travesia de Manises de la CV-370 desde Avenida dels Tranvies hasta la V-11 de acceso al aeropuerto y sustitución del alumbrado del puente de la CV-371 en el término de Manises | K16: 3034000P | L16: Abierto simplificado | M16: 2 | N16: G4-3 | O16: 0 | P16: Oferta económica 70 | Amplliación del plazo de garantia 30 | T16: 45233222; 45233252; 45233223; 45233251; 34928530; 34991000; 50232100 | U16: PCAP | V16: PPT | W16: Ver | X16: 46310
B17: 46323.999 | C17: =IF(B17="","",INT(B17)-TODAY()) | D17: 812294 | E17: 812294 | F17: Comunitat Valenciana | G17: Valencia | H17: el Genovés | I17: Pleno del Ayuntamiento de Genovés | J17: Construcción de un edificio de nueva planta, destinado a la población joven de la localidad, emplazado en calle Maestro Serrano nº 4 de El Genovés. | K17: 2222/2026 | L17: Abierto simplificado | M17: 10 | N17: C*-3 | O17: 0 | P17: Mejor oferta económica 100 | Q17: definitiva 5% | T17: 45000000; 45220000; 45200000 | U17: PCAP | V17: PPT | W17: Ver | X17: 46310
B18: 46323.999 | C18: =IF(B18="","",INT(B18)-TODAY()) | D18: 675994.61 | E18: 743594.07 | F18: Comunitat Valenciana | G18: Valencia | I18: Junta de Gobierno del Ajuntament de València | J18: Ejecución de las Obras denominadas Limpieza y mantenimiento de las fachadas del Mercado Central de València.- | K18: 04101/2026/236-O | L18: Abierto simplificado | M18: 5 | N18: K7-3 | O18: 0 | P18: REDUCCIÓN DEL PLAZO DE EJECUCIÓN 20 | BAJA ECONÓMICA AL PRESUPUESTO BASE DE LICITACIÓN 40 | EXPERIENCIA PROFESIONAL ESPECÍFICA DE LAS PERSONAS INTEGRANTES DEL EQUIPO DE TRABAJO 30 | AMPLIACIÓN PLAZO DE GARANTIA 10 | Q18: definitiva 5% | T18: 45213141 | U18: PCAP | V18: PPT | W18: Ver | X18: 46310
B19: 46324.5 | C19: =IF(B19="","",INT(B19)-TODAY()) | D19: 20327127 | E19: 21140212 | F19: Andalucía | G19: Málaga | H19: Málaga | I19: Aena. Consejo de Administración | J19: Actuaciones En Pavimento En Rodadura A Y Salidas Asociadas. Aeropuerto De Málaga - Costa Del Sol. | K19: DIN-442/2026 | L19: Licitación con negociación | M19: 37 | O19: 0 | P19: Precio 100 | T19: 45235311 | U19: PCAP | V19: PPT | W19: Ver | X19: 46314
B20: 46324.583 | C20: =IF(B20="","",INT(B20)-TODAY()) | D20: 743801.65 | E20: 743801.65 | F20: Andalucía | G20: Sevilla | I20: Alcaldia del Ayuntamiento de Pilas | J20: Ejecución de la obra "Proyecto de reasfaltado 2026, de Pilas (Sevilla). | K20: P4107500C-2026/000082-PAAS | L20: Abierto simplificado | M20: 6 | N20: G4-3; G*-3 | O20: 0 | P20: Reducción del plazo de ejecución [2] 10 | Aspecto Económico (precio) [1] 75 | Mejoras [3] 15 | T20: 45233222 | U20: PCAP | V20: PPT | W20: Ver | X20: 46310
B21: 46324.625 | C21: =IF(B21="","",INT(B21)-TODAY()) | D21: 799446.19 | E21: 959335.43 | F21: Andalucía | G21: Málaga | H21: Torre de Benagalbón, término municipal de Rincón de la Victoria | I21: Alcaldía del Ayuntamiento de Rincón de la Victoria | J21: Aparcamientos en sótano del Pabellón Rubén Ruzafa | K21: Contratación 57/26 | L21: Abierto simplificado | M21: 8 | N21: C4-3 | O21: 0.25 | P21: Reducción del plazo de ejecución al estipulado en el PCAP 30 | Programa de los trabajos compatibilizando la ejecución de obra con el funcionamiento del Pabellón 10 (JV) | Memoria de desarrollo del proyecto, las obras y propuestas para la mejora de la eficiencia y calidad de los trabajos 15 (JV) | Oferta económica 30 | Ampliación del plazo de garantía a añadir al estipulado en el PCAP 15 | Q21: definitiva 5% | R21: No procede (Punto 6 del Anexo I) | T21: 45000000; 45223310 | U21: PCAP | V21: PPT | W21: Ver | X21: 46317 | Y21: 2026-10-23: plazo 2026-10-26 15:00 → 2026-10-29 15:00
B22: 46324.999 | C22: =IF(B22="","",INT(B22)-TODAY()) | D22: 667189.24 | E22: 667189.24 | F22: Andalucía | G22: Huelva | H22: ISLA CRISTINA | I22: Alcaldía del Ayuntamiento de Isla Cristina | J22: Obras Proyecto de renovación y mejora de la eficiencia energética de las instalaciones de alumbrado público exterior del municipio de Isla Cristina. | K22: 5773/2026 | L22: Abierto simplificado | M22: 6.1 | N22: I1-3 | O22: 0.25 | P22: Ampliación plazo garantía 10 | Calidad técnica de la propuesta de ejecución 25 (JV) | Oferta económica 60 | Primera intervención efectiva ante incidencias cubiertas por la garantía 5 | Q22: definitiva 5% | T22: 45316100; 45315600 | U22: PCAP | V22: PPT | W22: Ver | X22: 46310
B23: 46324.999 | C23: =IF(B23="","",INT(B23)-TODAY()) | D23: 568417.81 | E23: 568417.81 | F23: Andalucía | G23: Huelva | H23: BONARES | I23: Alcaldia del Ayuntamiento de Bonares | J23: Creación de aparcamiento y plaza pública ajardinada en Avda. Nuestra Señora del Rocío nº 3 de Bonares (Huelva | K23: 4654/2026 | L23: Abierto simplificado | M23: 12 | N23: C*-3 | O23: 0 | P23: REDUCCIÓN DEL PLAZO DE EJECUCIÓN 12 | OFERTA ECONÓMICA 68 | AUMENTO PLAZO DE GARANTÍA 20 | Q23: definitiva 5% | R23: No se prevé la revisión de precios (Cláusula 6.9. del PCAP). | T23: 45220000; 45223000; 45000000 | U23: PCAP | V23: PPT | W23: Ver | X23: 46310
B24: 46325.583 | C24: =IF(B24="","",INT(B24)-TODAY()) | D24: 1540129.7 | E24: 1540129.7 | F24: Andalucía | G24: Granada | H24: Granada | I24: Secretaría General de la Agencia Estatal Consejo Superior de Investigaciones Científicas | J24: Obras de nuevo edificio del Instituto de Astrofísica de Andalucía | K24: 35349/26 | L24: Abierto simplificado | M24: 12 | O24: 0.25 | P24: Documentación complementaria 4 (JV) | Características técnicas del control de calidad de la ejecución de la obra 3 (JV) | Plan de mantenimiento técnico-legal 15 | Estudio del proyecto 8 (JV) | Memoria de ejecución de las obras y análisis y programa de trabajos 10 (JV) | Porcentaje ofertado de control de calidad 8 | Ampliación del plazo de garantía 12 | Oferta economica 40 | T24: 45214000; 45214600; 45213150 | U24: PCAP | V24: PPT | W24: Ver | X24: 46310
B25: 46328.333 | C25: =IF(B25="","",INT(B25)-TODAY()) | D25: 1189873.9 | E25: 1189873.9 | F25: Comunitat Valenciana | G25: Alicante | H25: ORIHUELA | I25: Junta de Gobierno del Ayuntamiento de Orihuela | J25: Rehabilitación de Paramentos y Acondicionamiento de Sala de hombres en el Museo Arqueológico Comarcal de Orihuela | K25: 4727/2026 BIS | L25: Abierto simplificado | M25: 12 | N25: C*-3; K7-3 | O25: 0.25 | P25: Ampliación del plazo de garantía 30 | OFERTA ECONÓMICA (Sin IVA) 45 | Estudio de unidades de obra del proyecto 15 (JV) | Estudio de mediciones del proyecto 10 (JV) | Q25: complementaria 5%; definitiva 5% | T25: 45000000; 45454100; 45453000 | U25: PCAP | V25: PPT | W25: Ver | X25: 46310
B26: 46328.583 | C26: =IF(B26="","",INT(B26)-TODAY()) | D26: 557102.23 | E26: 557102.23 | F26: Comunitat Valenciana | G26: Valencia | H26: REQUENA | I26: Junta de Gobierno Local del Ayuntamiento de Requena | J26: Demolicion y construccion Centro Social de Campo Arcís | K26: 2896352M | L26: Abierto simplificado | M26: 24 | O26: 0 | P26: Mejora en el Precio, 100 puntos 100 | Q26: definitiva 5% | T26: 45211350; 45111100 | U26: PCAP | V26: PPT | W26: Ver | X26: 46310
B27: 46328.583 | C27: =IF(B27="","",INT(B27)-TODAY()) | D27: 814296.7 | E27: 814296.7 | F27: Comunitat Valenciana | G27: Valencia | H27: Turís | I27: Alcaldía del Ayuntamiento de Turis | J27: Urbanización calles perimetrales parcela nuevo CEIP | K27: 3385/2026 | L27: Abierto simplificado | M27: 5 | O27: 0 | P27: Precio 100 | Q27: definitiva 5% | T27: 45233140 | U27: PCAP | V27: PPT | W27: Ver | X27: 46310
B28: 46328.583 | C28: =IF(B28="","",INT(B28)-TODAY()) | D28: 40000000 | E28: 80000000 | F28: Andalucía | G28: Almería | I28: Empresa de Transformación Agraria S.A.,S.M.E., M.P., (TRAGSA) | J28: Conclusión del Acuerdo Marco Para La Contratación de Las Obras Alquiler De Maquinaria De Obra Civil, Agrícola y Forestal, y Camiones, Dotada de Operario, Para Las Actuaciones de La Gerencia Provincial de Tragsa en Almería, Incluidas Obras Financiadas Con Fondos Europeos | K28: TSA0084163 | L28: Abierto | M28: 24 | N28: D*-1; A*-1; K*-1; C*-1; G*-1; E*-1 | O28: 0 | P28: Precio de la oferta 100 | R28: No | T28: 45500000 | U28: PCAP | V28: PPT | W28: Ver | X28: 46314 | Y28: 2026-10-20: estado PRE → PUB
B29: 46328.999 | C29: =IF(B29="","",INT(B29)-TODAY()) | D29: 4502927.3 | E29: 4502927.3 | F29: Comunitat Valenciana | G29: Valencia | I29: Pleno del Ayuntamiento de Carlet | J29: Obras de restitución de las canalizaciones de la red de agua potable y de la red de saneamiento y pavimentación de la Ronda Malecón, financiadas con cargo al Fondo de Solidaridad de la Unión Europea | K29: 3018/2026 | L29: Abierto | M29: 12 | N29: E*-5 | O29: 0 | P29: Ampliación del plazo de garantía 10 | Uso de materiales con menor huella de carbono 20 | Reducción del plazo de ejecución 20 | Oferta económica 50 | Q29: definitiva 5% | T29: 45240000; 45233200; 45232150; 45232440 | U29: PCAP | V29: PPT | W29: Ver | X29: 46310
B30: 46329.458 | C30: =IF(B30="","",INT(B30)-TODAY()) | D30: 590000 | E30: 590000 | F30: Andalucía | G30: Cádiz | I30: Comité Central de Compras de Navantia S.A., S.M.E. | J30: Licitación para la adjudicación de un Contrato para los trabajos de rehabilitación de accesos, protecciones colectivas y líneas de vida en grúas en Navantia Cádiz. | K30: 5100075545 Líneas Vida Grúas Navantia Cádiz | L30: Normas internas | M30: 7 | O30: 1 | P30: Según PPT y PCP 100 (JV) | T30: 45262600; 45340000 | U30: PCAP | V30: PPT | W30: Ver | X30: 46310 | Y30: 2026-10-26: plazo 2026-10-28 12:00 → 2026-11-03 11:00
B31: 46329.5 | C31: =IF(B31="","",INT(B31)-TODAY()) | D31: 41658023 | E31: 43324344 | F31: Comunitat Valenciana | G31: Valencia | H31: Valencia / València | I31: Aena. Consejo de Administración | J31: Recrecido De Pista, Adecuación De Calles De Rodaje Y Mejora Del Camino Perimetral. Aeropuerto De Valencia | K31: DIN-350/2026 | L31: Licitación con negociación | M31: 27 | O31: 0 | P31: Precio 100 | T31: 45235000 | U31: PCAP | V31: PPT | W31: Ver | X31: 46317
B32: 46329.583 | C32: =IF(B32="","",INT(B32)-TODAY()) | D32: 988010.83 | E32: 988010.83 | F32: Andalucía | G32: Sevilla | H32: Gines | I32: Junta de Gobierno Local del Ayuntamiento de Gines | J32: Obras de rehabilitación y adecuación de inmueble municipal en plantas baja y sótano para aparcamiento público municipal y locales de usos culturales y sociales. | K32: 6859/2026 | L32: Abierto simplificado | M32: 6 | N32: C*-2 | O32: 0.25 | P32: AMPLIACIÓN DEL PLAZO DE GARANTÍA DE LAS OBRAS 10 | VALORACIÓN DE RESIDUOS DE CONSTRUCCIÓN Y DEMOLICIÓN 5 | MEJORA 2: SISTEMA DE MONITORIZACIÓN ENERGÉTICA 5 | MEMORIA TÉCNICA DE EJECUCIÓN DE LA OBRA 10 (JV) | OFERTA ECONÓMICA 45 | PLAN DE MINIMIZACIÓN DE AFECCIONES AL ENTORNO 5 (JV) | PLAN DE COORDINACIÓN CON LA ACTIVIDAD MUNICIPAL Y LOS EQUIPAMIENTOS ADYACENTES 5 (JV) | MEJORA 1: CANALIZACIONES ADICIONALES 5 | CONTROL DE CALIDAD ADICIONAL 5 | PLAN DE INFORMACIÓN PÚBLICA Y DE GESTIÓN DE INCIDENCIAS 5 (JV) | Q32: definitiva 5% | T32: 45453100; 45313100; 45331210 | U32: PCAP | V32: PPT | W32: Ver | X32: 46310
B33: 46329.792 | C33: =IF(B33="","",INT(B33)-TODAY()) | D33: 669122.06 | E33: 669122.06 | F33: Andalucía | G33: Córdoba | H33: Córdoba | I33: Presidencia del Consejo de Administración de la Empresa Provincial de Aguas de Córdoba S.A. | J33: Obra de Red de Abastecimiento Aldea del Villar (Fuente Palmera). | K33: CC 55/2026 | L33: Abierto | M33: 12 | N33: E1-3 | O33: 0.5 | P33: Ampliación plazo de garantía 10 (JV) | Oferta económica 50 | Oferta técnica 40 (JV) | T33: 45240000 | U33: PCAP | V33: PPT | W33: Ver | X33: 46310
B34: 46329.792 | C34: =IF(B34="","",INT(B34)-TODAY()) | D34: 1071077.5 | E34: 1071077.5 | F34: Andalucía | G34: Almería | H34: Almería | I34: Presidencia de la Autoridad Portuaria de Almería | J34: Obras de Reforma de Pasarelas 4 y 5 en Puerto de Almería | K34: 31/O/A/AL26 | L34: Abierto | M34: 12 | N34: C3-4 | O34: 0.25 | P34: Cuantitativos 75 | Cualitativos 25 (JV) | T34: 45223210; 45223100 | U34: PCAP | V34: PPT | W34: Ver | X34: 46310
B35: 46329.792 | C35: =IF(B35="","",INT(B35)-TODAY()) | D35: 13104057 | E35: 13104057 | F35: Andalucía | G35: Jaén | I35: Pleno del Ayuntamiento de Jaén | J35: Contratación de las obras de reparación de pavimentos de calles del municipio de Jaén tras concatenación de borrascas durante los meses de enero y febrero de 2026, financiadas por la Administración General del Estado, a través del Ministerio de Política Territorial y Memoria Democrática, al amparo del art. 7 del Real Decreto-Ley 5/2026, de 17 de febrero. | K35: 2026000083 | L35: Abierto | M35: 4 | O35: 0.25 | P35: Proceso constructivo 10 (JV) | Precio 55 | Disponibilidad para trabajos nocturnos 10 | Programa de trabajo 15 (JV) | Plazo de garantía 10 | Q35: definitiva 5% | S35: 6 | T35: 45233252; 45111100; 45262300; 45262522 | U35: PCAP | V35: PPT | W35: Ver | X35: 46310
B36: 46329.792 | C36: =IF(B36="","",INT(B36)-TODAY()) | D36: 1565254.7 | E36: 1565254.7 | F36: Andalucía | G36: Almería | H36: Almería | I36: Presidencia de la Autoridad Portuaria de Almería | J36: Obras de reforma de Pasarelas 2 y 3 en Puerto de Almería | K36: 26/O/A/AL26 | L36: Abierto | M36: 6 | N36: C3-4 | O36: 0.25 | P36: Cuantitativos 75 | Cualitativos 25 (JV) | T36: 45223210; 45223100 | U36: PCAP | V36: PPT | W36: Ver | X36: 46310
B37: 46329.999 | C37: =IF(B37="","",INT(B37)-TODAY()) | D37: 564012.4 | E37: 564012.4 | F37: Comunitat Valenciana | H37: Oliva | I37: Concejal de Contratación del Ayuntamiento de Oliva | J37: Mejora de la accesibilidad en espacios públicos y renovación de la red de abastecimiento de agua potable | K37: 15056/2026 | L37: Abierto simplificado | M37: 5 | O37: 0 | P37: Ampliación adicional plazo de garantía 10 | Baja económica en el tipo de licitación 20 | Conjunto de mejoras 70 | Q37: definitiva 5%; complementaria 2% | T37: 45200000 | U37: PCAP | V37: PPT | W37: Ver | X37: 46310
B38: 46329.999 | C38: =IF(B38="","",INT(B38)-TODAY()) | D38: 1106611.6 | E38: 1106611.6 | F38: Andalucía | G38: Sevilla | I38: Alcaldía del Ayuntamiento de Alcalá del Río | J38: Contrato de obras relativo al Proyecto básico y de ejecución de Reforma y Acondicionamiento de la Piscina Municipal y el entorno periférico | K38: P4100500J-2026/000021-PAAS | L38: Abierto simplificado | M38: 16 | N38: J2-2; C3-2; C*-2; J*-2 | O38: 0 | P38: Aspecto Económico (precio) [1] 40 | Mejora 1 Nuevo sistema de Riego para las zonas de césped [2] 20 | Mejora 2 Retirada y renovación del césped [3] 40 | T38: 45212220 | U38: PCAP | V38: PPT | W38: Ver | X38: 46310
B39: 46329.999 | C39: =IF(B39="","",INT(B39)-TODAY()) | D39: 3060580.6 | E39: 3060580.6 | F39: Andalucía | G39: Huelva | I39: Pleno del Ayuntamiento de Punta umbría | J39: Ejecución de las obras para la renovación y mejora de la eficiencia energética de las instalaciones de alumbrado público exterior en el Municipio de Punta Umbría (Huelva) | K39: 5163/2026 | L39: Abierto | M39: 9 | N39: I1-4 | O39: 0.25 | P39: Memoria Técnica 25 (JV) | Reducción de Plazos 20 | Oferta económica 35 | Experiencia Profesional 20 | Q39: definitiva 5% | T39: 45316100; 45315600; 34928500 | U39: PCAP | V39: PPT | W39: Ver | X39: 46310
B40: 46329.999 | C40: =IF(B40="","",INT(B40)-TODAY()) | D40: 2370624.5 | E40: 2844749.4 | F40: Andalucía | G40: Almería | I40: Junta de Gobierno Local del Ayuntamiento de El Ejido | J40: Es objeto de la presente licitación es la contratación de la ejecución del proyecto de obras denominado: Proyecto de construcción de adecuación del complejo deportivo en el núcleo de Almerimar. Fase II, conforme a las especificaciones y características expuestas en el presente pliego y en el proyecto técnico. | K40: 2026 1137 | L40: Abierto | M40: 6 | O40: 0.25 | P40: Proposición económica 75 | Criterios evaluables mediante un juicio de valor 25 (JV) | Q40: provisional 5% | T40: 45200000 | U40: PCAP | V40: PPT | W40: Ver | X40: 46310
B41: 46329.999 | C41: =IF(B41="","",INT(B41)-TODAY()) | D41: 2153684.3 | E41: 2153684.3 | F41: Comunitat Valenciana | G41: Valencia | H41: Torrent | I41: Junta de Gobierno del Ayuntamiento de Torrent | J41: Obras de mejora de baños, eficiencia energética, accesibilidad, patios, adaptación al CTE del CEIP Virgen del Rosario de Torrent, en el marco del Pla Edificant | K41: 32643/2026 | L41: Abierto | M41: 12 | O41: 0 | P41: Oferta económica 100 | Q41: definitiva 5% | T41: 45214210 | U41: PCAP | V41: PPT | W41: Ver | X41: 46317
B42: 46329.999 | C42: =IF(B42="","",INT(B42)-TODAY()) | D42: 563608.27 | E42: 563608.27 | F42: Andalucía | G42: Málaga | I42: Alcaldía del Ayuntamiento de Ronda | J42: C. Obras. Proyecto de Adecuación de solar colindante a la Estación de Ferrocarril para aparcamiento de vehículos de Ronda (Málaga). | K42: 17561/2026 | L42: Abierto | M42: 10 | N42: G6-3 | O42: 0 | P42: Mejor precio ofertado por los licitadores 90 | Incremento del plazo de garantía previsto 10 | Q42: definitiva 5% | T42: 45000000; 45233140 | U42: PCAP | V42: PPT | W42: Ver | X42: 46317
B43: 46329.999 | C43: =IF(B43="","",INT(B43)-TODAY()) | D43: 1221212.3 | E43: 1221212.3 | F43: Andalucía | G43: Córdoba | I43: Junta de Gobierno de la Diputación Provincial de Córdoba | J43: Nuevo campo de fútbol de césped artificial en el SG-D6 y SG-V7 "LLanos de Cristo" del PGOU vigente, en Puente Genil (Córdoba). Obra incluida en el Plan Provincial de Obras y Servicios 2024-2027 (bienio 2025-2026) | K43: 646/26 BIS | L43: Abierto | M43: 12 | O43: 0 | P43: Compromiso de ampliación del plazo de garantía de la obra 20 | Oferta económica respecto al presupuesto base de licitación 80 | Q43: definitiva 5%; complementaria 5% | T43: 45200000; 45212221; 45212200; 45212224; 45212213; 45212230 | U43: PCAP | V43: PPT | W43: Ver | X43: 46317
B44: 46330.792 | C44: =IF(B44="","",INT(B44)-TODAY()) | D44: 5022149.1 | E44: 5022149.1 | F44: Andalucía | G44: Cádiz | H44: TARIFA | I44: Pleno del Ayuntamiento de Tarifa | J44: construcción de 59 viviendas en alquiler social en edificios energéticamente eficientes, en el marco del capítulo VII del Real Decreto 853/2021, de 5 de octubre, por el que se regulan los programas de ayuda en materia de rehabilitación residencial y vivienda social del Plan de Recuperación, transformación y resiliencia, mediante procedimiento simplificado urgente | K44: 2026/8791 | L44: Abierto simplificado | M44: 18 | N44: C*-5 | O44: 0 | P44: mejora del plazo de ejecucion 10 | oferta economica 75 | MEJORA DEL SERVICIO DE MANTENIMIENTO DE APARATOS ELEVADORES (ASCENSORES) 5 | MEJORA DEL PLAZO DE GARANTÍA 10 | Q44: definitiva 5% | T44: 45211000 | U44: PCAP | W44: Ver | X44: 46317
B45: 46330.999 | C45: =IF(B45="","",INT(B45)-TODAY()) | D45: 617734.71 | E45: 617734.71 | F45: Andalucía | G45: Huelva | H45: BONARES | I45: Alcaldia del Ayuntamiento de Bonares | J45: Mejora de las instalaciones deportivas en el Polígono Industrial El Corchito. | K45: 3624/2026 | L45: Abierto simplificado | M45: 8 | O45: 0 | P45: [lote 1] | MEJORA DE LA DENSIDAD DE LA FIBRA (MEJORAS DEL CÉSPED ARTIFICIAL) 10 | AUMENTO DE GARANTÍA LOTE 1 10 | DENSIDAD DE FILAMENTOS (MEJORAS DEL CÉSPED ARTIFICIAL) 5 | MEJORA CALIDAD Y CARACTERÍSTICAS (MEJORAS DEL CÉSPED ARTIFICIAL) 10 | MEJORA DE LOS CRITERIOS MEDIOAMBIENTALES (MEJORAS DEL CÉSPED ARTIFICIAL) 15 | CALIDAD VISUAL MEDIANTE DIFERENTES TONALIDADES DEL CÉSPED (MEJORAS DEL CÉSPED ARTIFICIAL) 11 | MEJORA DE CALIDAD EN PESO TOTAL DE LA FIBRA (MEJORAS DEL CÉSPED ARTIFICIAL) 5 | OTRAS MEJORAS (MEJORAS DEL CÉSPED ARTIFICIAL) 14 | OFERTA ECONÓMICA LOTE 1 15 | MEJORA CALIDAD AUMENTANDO EL ESPESOR DEL FILAMENTO (MEJORAS DEL CÉSPED ARTIFICIAL) 5 | Q45: definitiva 5% | R45: No se prevé la revisión de precios (Cláusula 6.9. del PCAP). | S45: 3 | T45: 45212200; 43324000; 45236119; 45315300; 45261210; 09331200; 39293400; 39522100; 45232453; 45421144; 45261215 | U45: PCAP | V45: PPT | W45: Ver | X45: 46311
B46: 46330.999 | C46: =IF(B46="","",INT(B46)-TODAY()) | D46: 1846516.6 | E46: 1846516.6 | F46: Andalucía | G46: Sevilla | H46: Bormujos | I46: Alcaldía del Ayuntamiento de Bormujos | J46: Ejecución de las obras de “Remodelación de Bulevar Avenida San Juan de Dios”. | K46: 12483/2026 | L46: Abierto simplificado | M46: 5 | N46: G6-4 | O46: 0.2 | P46: Mejora Video en 3D resultado de la obra 5 | Memoria Descriptiva 20 (JV) | Oferta Económica 75 | Q46: definitiva 5% | T46: 45233252 | U46: PCAP | V46: PPT | W46: Ver | X46: 46311
B47: 46331.999 | C47: =IF(B47="","",INT(B47)-TODAY()) | D47: 2543636.1 | E47: 2543636.1 | F47: Andalucía | G47: Sevilla | I47: Presidencia de la Diputación Provincial de Sevilla | J47: Obra para la mejora de la estación de bombeo de agua potable al Consorcio de Aguas Sierra Sur, nuevo depósito y sistemas antiariete, Osuna | K47: 2026/000697-PAA | L47: Abierto | M47: 8 | N47: E1-5 | O47: 0.25 | P47: Calidad [1] 25 (JV) | Aspecto Económico (precio) [1] 75 | T47: 45213260; 45232152 | U47: PCAP | V47: PPT | W47: Ver | X47: 46310
B48: 46331.999 | C48: =IF(B48="","",INT(B48)-TODAY()) | D48: 952036.08 | E48: 952036.08 | F48: Comunitat Valenciana | G48: Castellón | H48: Burriana (Castellón) | I48: Alcaldía del Ayuntamiento de Borriana | J48: Son objeto de contratación: - Lote 1 Obras de ejecución del proyecto "Dotación de accesibilidad al polideportivo Sant Blai de Burriana" - Lote 2 Obras de ejecución del proyecto "Mejora de las condiciones de estanqueidad del polideportivo municipal Sant Blai en Burriana" | K48: BURR16660/2026-PM9-PM 10 | L48: Abierto simplificado | M48: 7 | O48: 0 | P48: Plazo de ejecución del contrato 25 | Oferta económica 75 | Q48: complementaria 2%; definitiva 5% | R48: No | S48: 2 | T48: 45000000; 45212221; 45261000; 45443000; 45200000; 45212200 | U48: PCAP | V48: PPT | W48: Ver | X48: 46314
B49: 46331.999 | C49: =IF(B49="","",INT(B49)-TODAY()) | D49: 810884.09 | E49: 810884.09 | F49: Comunitat Valenciana | G49: Castellón | I49: Junta de Gobierno del Ayuntamiento de Borriana | J49: Ejecución de las obras "Acondicionamiento del Cami Fondo entre la avda. Vicente Cañada Blanch y la avda. Unión Europea" (PM 8/2026). | K49: BURR 16353/2026-PM 8/2026 | L49: Abierto simplificado | M49: 6 | N49: G4-3 | O49: 0.25 | P49: B.2. Aumento del plazo de garantía de la obra 15 | A.1 Conocimiento del proyecto aprobado 25 (JV) | B.1. Oferta económica 60 | Q49: complementaria 2%; definitiva 5% | R49: No | T49: 45230000 | U49: PCAP | V49: PPT | W49: Ver | X49: 46314
B50: 46331.999 | C50: =IF(B50="","",INT(B50)-TODAY()) | D50: 691158.8 | E50: 691158.8 | F50: Andalucía | G50: Córdoba | H50: Villa del Río | I50: Alcaldía del Ayuntamiento de Villa del Río | J50: Redacción del proyecto de ejecución a partir de proyecto básico, redacción de estudio de seguridad y salud, proyectos de instalaciones y de actividad y ejecución de obras para la construcción de edificio destinado a biblioteca pública municipal y salas de usos múltiples (primera fase). | K50: 8223/2026 | L50: Abierto simplificado | M50: 20 | O50: 0 | P50: Pluralidad de criterios 100 | Q50: definitiva 5% | T50: 45212330; 71317200; 71242000; 45212170; 71000000 | U50: PCAP | V50: PPT | W50: Ver | X50: 46317
A51: SÍ | B51: 46331.999 | C51: =IF(B51="","",INT(B51)-TODAY()) | D51: 5236971.6 | E51: 5236971.6 | F51: Andalucía | G51: Huelva | H51: HUELVA | I51: Junta de Gobierno de la Diputación Provincial de Huelva | J51: El presente contrato tiene por objeto la rehabilitación del firme de diversas carreteras provinciales pertenecientes al Plan de inversiones del Servicio de Carreteras y Caminos 2025 y Tu Diputación Actua. | K51: 2026/CMY_03/000148 | L51: Abierto | M51: 3 | O51: 0 | P51: REDUCCIÓN DEL PLAZO DE EJECUCIÓN 15 | MEJORA EN EL IMPORTE A DEDICAR AL CONTROL DE CALIDAD OBLIGATORIO 15 | Incremento del Plazo de Garantía 15 | PRECIO 55 | Q51: definitiva 5% | S51: 6 | T51: 45233000 | U51: PCAP | V51: PPT | W51: Ver | X51: 46321
B52: 46332.417 | C52: =IF(B52="","",INT(B52)-TODAY()) | D52: 638220.99 | E52: 638220.99 | F52: Andalucía | G52: Huelva | I52: Empresa de Transformación Agraria S.A.,S.M.E., M.P., (TRAGSA) | J52: Suministro y ejecución de instalaciones eléctricas, seguridad, comunicaciones y fotovoltaica en edificio administrativo de Huelva, en Plaza de La Constitución, No1, Huelva | K52: TSA0083804 | L52: Abierto simplificado | M52: 18 | O52: 0 | P52: PRECIO 100 | Q52: definitiva 5% | R52: No aplica la revisión de precios en esta licitación | S52: 3 | T52: 45315600; 45315500; 45310000 | U52: PCAP | V52: PPT | W52: Ver | X52: 46314
B53: 46332.5 | C53: =IF(B53="","",INT(B53)-TODAY()) | D53: 1959412 | E53: 1959412 | F53: Comunitat Valenciana | G53: Alicante | H53: Almoradí | I53: Junta de Gobierno del Ayuntamiento de Almoradí | J53: Obras “Actuación 3.1. Reurbanización de la Avda. Dr. Marañón. Mejora de acceso al Centro Comercial, Tipo de Acción 4, Subtipo 4.1 y la Actuación 3.2. Infraestructura ciclista en la Avda. Dr. Marañón, Tipo de Acción 2, Subtipo 2.3, en el marco del Plan de Actuación Integrado de Almoradí, operación cofinanciada por el Fondo Europeo de Desarrollo Regional (FEDER)”. | K53: 7981/2026 | L53: Abierto simplificado | M53: 5 | O53: 0.25 | P53: Memoria Técnica 25 (JV) | Proposición Económica 75 | Q53: definitiva 5%; complementaria 5% | T53: 45233200; 45211360; 45233253; 45111100; 45233162; 45000000; 45233140 | U53: PCAP | W53: Ver | X53: 46314
B54: 46332.542 | C54: =IF(B54="","",INT(B54)-TODAY()) | D54: 30728972 | E54: 30728972 | F54: Andalucía | G54: Jaén | H54: JAEN | I54: Consejo de Administración de Sociedad Mercantil Estatal Aguas de las Cuencas de España, S.A. (ACUAES) | J54: Ejecución de las obras del Proyecto de construcción de la Nueva Planta de tratamiento de agua potable del Rumblar (Jaén) | K54: ACE/318.50/26/OBRA/01 | L54: Abierto | M54: 26 | N54: K8-4 | O54: 0.45 | P54: Compromiso de ampliación del plazo de garantía 10 | Oferta evaluable conforme a criterios dependientes de juicios de valor - Oferta técnica 45 (JV) | Criterios cuantificables mediante la mera aplicación de fórmulas 45 | Q54: complementaria 5%; definitiva 5% | R54: Fórmula referida a obras hidráulicas nº 561 | T54: 45252120 | U54: PCAP | V54: PPT | W54: Ver | X54: 46311
B55: 46332.542 | C55: =IF(B55="","",INT(B55)-TODAY()) | D55: 3949255.5 | E55: 4344181 | F55: Comunitat Valenciana | G55: Valencia | I55: Presidencia de la Diputación Provincial de Valencia | J55: Ac-576A/O. Ampliación de plataforma y mejora del drenaje de la carretera CV-598 de Autovía A35 a Canals en los términos municipales de Montesa y Canals. | K55: 59/19/CAR | L55: Abierto | M55: 15 | N55: G4-5 | O55: 0.46 | P55: 1. Oferta económica 54 | 2. Garantía de suministro 26 (JV) | 3. Programa de trabajos 20 (JV) | Q55: complementaria 5%; definitiva 5% | T55: 45233120 | U55: PCAP | W55: Ver | X55: 46317
B56: 46332.999 | C56: =IF(B56="","",INT(B56)-TODAY()) | D56: 1089694.1 | E56: 1089694.1 | F56: Andalucía | G56: Sevilla | I56: Alcaldia del Ayuntamiento de San Nicolás del Puerto | J56: PAS. Construcción de Piscina Municipal y de vesturarios en San Nicolás del Puerto. Plan ACTUA 2022 Diputación. | K56: P4108800F-2026/000032-PAAS | L56: Abierto simplificado | M56: 10 | N56: C6-6; C*-4; C4-4 | O56: 0 | P56: Aspecto Económico (precio) [1] 100 | T56: 45000000 | U56: PCAP | V56: PPT | W56: Ver | X56: 46310
B57: 46335.792 | C57: =IF(B57="","",INT(B57)-TODAY()) | D57: 1240704.7 | E57: 1488845.7 | F57: Comunitat Valenciana | G57: Alicante | H57: Alicante (Alacant) | I57: Alcaldía del Ayuntamiento de Santa Pola | J57: Licitación para la contratación de las Obras de Reforma y adecuación del campo municipal Manolo Maciá de Santa Pola, susceptible de ser confinanciado por la UE a través del Fondo Europeo de Desarrollo | K57: 18226/2026 | L57: Abierto simplificado | M57: 4 | N57: G*-3 | O57: 0.45 | P57: A.2. AMPLIACIÓN DE GARANTÍA 15 (JV) | A.3. SOSTENIBILIDAD AMBIENTAL EN LA EJECUCIÓN 30 (JV) | A.1. OFERTA ECONÓMICA 55 | T57: 45212200; 45212224; 45212220; 45310000 | U57: PCAP | V57: PPT | W57: Ver | X57: 46315
B58: 46335.999 | C58: =IF(B58="","",INT(B58)-TODAY()) | D58: 929839.95 | E58: 929839.95 | F58: Andalucía | G58: Córdoba | H58: CABRA | I58: Alcaldía del Ayuntamiento de Cabra | J58: Servicio de redacción del proyecto básico y ejecución de obras, coordinación en materia de seguridad y salud durante la elaboración del proyecto, estudio de libro del edificio y la posterior ejecución de las obras de construcción de seis viviendas en alquiler social en edificios energéticamente eficientes, en el marco del capítulo VII del real decreto 853/2021 de 5 de octubre | K58: 2026/21080 | L58: Abierto | M58: 12 | O58: 0 | P58: Redacción proyecto en formato BIM 10 | Menor precio ofertado sobre el precio de licitación, hasta un máximo de 75 puntos. 75 | Compromiso de Ampliación de Plazo de Garantía 15 | Q58: definitiva 5% | T58: 45211000; 71200000 | U58: PCAP | V58: PPT | W58: Ver | X58: 46310
B59: 46335.999 | C59: =IF(B59="","",INT(B59)-TODAY()) | D59: 4895758.7 | E59: 4895758.7 | F59: Comunitat Valenciana | G59: Valencia | H59: Estivella | I59: Pleno del Ayuntamiento de Estivella | J59: Demolició i reposició del CENTRE CEIP EL BRAÇAL en la mateixa parcel·la | K59: 271/2026 | L59: Abierto | M59: 18 | N59: C*-5 | O59: 0.2 | P59: Planificación de los trabajos y conocimiento del proyecto (Hasta 5 puntos) 5 (JV) | Aumento del plazo de garantía 2 | Compromiso de realización de un reportaje fotográfico de la obra terminada 4 | Medidas para la reducción de los impactos generados en el entorno durante el proceso constructivo (Hasta 5 puntos) 5 (JV) | Compromiso de limpieza fina de obra 3 | Implantación y organización de la obra (Hasta 10 puntos) 10 (JV) | Compromiso de calidad en personal asignado 6 | Menor precio ofertado 65 | Q59: definitiva 5% | R59: Conforme al artículo 10 del PCAP. | T59: 45214000 | U59: PCAP | V59: PPT | W59: Ver | X59: 46310
B60: 46335.999 | C60: =IF(B60="","",INT(B60)-TODAY()) | D60: 4566296.3 | E60: 4566296.3 | F60: Andalucía | G60: Granada | H60: OGIJARES | I60: Presidencia de la Diputación Provincial de Granada | J60: Refundido final urbanización del Plan Especial "La Aurora" en Ogíjares. | K60: OB-037/26 | L60: Abierto | M60: 18 | N60: G6-5; E7-5; I9-4 | O60: 0 | P60: Ampliación del plazo de garantía 10 | El precio más bajo 90 | Q60: definitiva 5% | T60: 45220000; 45233252; 45232200; 45316110; 45232150; 45232410; 45233140 | U60: PCAP | V60: PPT | W60: Ver | X60: 46310
B61: 46335.999 | C61: =IF(B61="","",INT(B61)-TODAY()) | D61: 1793227 | E61: 1793227 | F61: Andalucía | G61: Granada | I61: Dirección Gerente de la Empresa Municipal de Abastecimiento y Saneamiento de Granada, S.A. | J61: Mejora de las infraestructuras y resiliencia hídrica en el ciclo integral del agua en la Avenida Don Bosco, entre la Avenida de Cádiz y la Avenida Fernando de los Ríos (Granada). | K61: Obra 2025-00017_3 | L61: Abierto | M61: 144 | N61: E*-4 | O61: 0.4 | P61: Oferta económica 60 | Oferta técnica 40 (JV) | T61: 45232150 | U61: PCAP | V61: PPT | W61: Ver | X61: 46310
B62: 46335.999 | C62: =IF(B62="","",INT(B62)-TODAY()) | D62: 1170584.1 | E62: 1170584.1 | F62: Andalucía | G62: Sevilla | I62: Pleno del Ayuntamiento de La Roda de Andalucía | J62: Contrato de obras para ejecución del "Proyecto básico y de terminación del pabellón polideportivo cubierto municipal" | K62: P4108200I-2026/000011-PAAS | L62: Abierto simplificado | M62: 18 | N62: C4-3 | O62: 0 | P62: Aspecto Económico (precio) [1] 100 | T62: 45000000 | U62: PCAP | V62: PPT | W62: Ver | X62: 46310 | Y62: 2026-10-22: plazo 2026-10-29 23:59 → 2026-11-09 23:59
B63: 46335.999 | C63: =IF(B63="","",INT(B63)-TODAY()) | D63: 638659.75 | E63: 638659.75 | F63: Comunitat Valenciana | G63: Valencia | I63: Alcaldía del Ayuntamiento de Quart de Poblet | J63: Proyecto de habilitación del local situado en la C/ Joanot Martorell, 6 para dependencias de la Policía Local del municipio de Quart de Poblet, incluido dentro del Pla Obert d´Inversions 24-27 de la Diputación Provincial e Valencia | K63: 2870452P | L63: Abierto simplificado | M63: 5 | O63: 0.25 | P63: Personal adscrito a la ejecución del contrato 15 | Mejoras 40 | Ampliación plazo garantía 20 | Metodología propuesta para la ejecución de los trabajos 25 (JV) | Q63: definitiva 5% | T63: 45000000; 45450000; 45213100 | U63: PCAP | V63: PPT | W63: Ver | X63: 46315
B64: 46335.999 | C64: =IF(B64="","",INT(B64)-TODAY()) | D64: 709293.76 | E64: 709293.76 | F64: Comunitat Valenciana | G64: Valencia | I64: Alcaldía del Ayuntamiento de Quart de Poblet | J64: Obra Proyecto de Mejora de la accesibilidad y de parte de las infraestructuras de la calle Jaume Balmes de Quart de Poblet, actuación incluida dentro del Plan Obert d´Inversions 24-27 de la Diputación Provincial de Valencia | K64: 2287483K | L64: Abierto simplificado | M64: 6 | N64: G6-2 | O64: 0.25 | P64: Mejoras vinculadas con el objeto del contrato 40 | Personal adscrito a la ejecución del contrato 15 | Ampliación plazo garantía 20 | Metodología propuesta para la ejecución de los trabajos 25 (JV) | Q64: definitiva 5% | T64: 45233140 | U64: PCAP | V64: PPT | W64: Ver | X64: 46315
B65: 46335.999 | C65: =IF(B65="","",INT(B65)-TODAY()) | D65: 527483.73 | E65: 527483.73 | F65: Andalucía | G65: Jaén | H65: Santisteban del Puerto | I65: Pleno del Ayuntamiento de Santisteban del Puerto | J65: Actuaciones de estabilización en el cerro de la Guaría en Santisteban del Puerto (Jaén). | K65: 611/2026 | L65: Abierto simplificado | M65: 6 | N65: K3-3; K2-3 | O65: 0 | P65: Plazo de garantía adicional 40 | Menor plazo de ejecución de obra 40 | Mejor oferta economica 20 | Q65: definitiva 5% | T65: 45111230; 45222000 | U65: PCAP | V65: PPT | W65: Ver | X65: 46315
B66: 46335.999 | C66: =IF(B66="","",INT(B66)-TODAY()) | D66: 661157.01 | E66: 661157.01 | F66: Andalucía | G66: Almería | I66: Junta de Gobierno del Ayuntamiento de Almería | J66: Contratación de obras de Reforma integral de la Plaza de la Iglesia y calles Iglesia de Cabo de Gata, La Estrella de Mar, Chozas y Las Barcas de la barriada de San Miguel de Cabo de Gata (Almería) | K66: AYAL-2026000221 | L66: Abierto simplificado | M66: 6 | O66: 0 | P66: CRITERIOS EVALUABLES MEDIANTE FÓRMULAS- oferta economica 55 | Criterios cualitativos objetivos - Aumento en la frecuencia de la presentación del Programa de Trabajos 10 | Criterios cualitativos objetivos - ampliacion del plazo inicial de garantia 35 | Q66: definitiva 5% | R66: No | T66: 45233140 | U66: PCAP | V66: PPT | W66: Ver | X66: 46315
B67: 46335.999 | C67: =IF(B67="","",INT(B67)-TODAY()) | D67: 1915620.7 | E67: 1915620.7 | F67: Andalucía | G67: Sevilla | H67: sevilla | I67: Comisión Ejecutiva del Patronato del Real Alcázar y Casa Consistorial de Sevilla | J67: Obra de intervencion y restauracion de la sala de exposiciones del real alcazar de sevilla | K67: 2026/000719 | L67: Abierto simplificado | M67: 9 | N67: K7-4 | O67: 0.2 | P67: Calidad técnica de la solución propuesta para la sobrecubierta andamiada provisional 20 (JV) | Mejora del equipo técnico 30 | Realización de memoria editada 10 | Ampliación del plazo de garantía 10 | OFERTA ECONÓMICA: 30 | Q67: complementaria 5%; definitiva 5% | R67: No | T67: 45212350 | U67: PCAP | V67: PPT | W67: Ver | X67: 46317
B68: 46335.999 | C68: =IF(B68="","",INT(B68)-TODAY()) | D68: 829996.61 | E68: 829996.61 | F68: Andalucía | G68: Huelva | I68: Junta de Gobierno del Ayuntamiento de Huelva | J68: Obras de renaturalización y ordenación de espacio público entorno calle Los Emires de Huelva. | K68: 906/2026/12 | L68: Abierto simplificado | M68: 6 | N68: G6-3 | O68: 0 | P68: Mejoras al proyecto 14 | Ampliación del plazo de garantía 10 | Oferta económica 66 | Experiencia del Jefe de Obra 10 | Q68: definitiva 5% | T68: 45111100; 45316000; 45233293; 45233252; 45262520; 45451300 | U68: PCAP | V68: PPT | W68: Ver | X68: 46317
B69: 46335.999 | C69: =IF(B69="","",INT(B69)-TODAY()) | D69: 1156866.8 | E69: 1156866.8 | F69: Andalucía | G69: Huelva | I69: Junta de Gobierno del Ayuntamiento de Huelva | J69: Ejecución de las obras del Plan de Asfaltado 2027. | K69: 497/2026 | L69: Abierto simplificado | M69: 6 | N69: G4-4 | O69: 0 | P69: Oferta económica 70 | Plazo de garantía 30 | Q69: definitiva 5% | S69: 2 | T69: 45233223; 45233221 | U69: PCAP | V69: PPT | W69: Ver | X69: 46317
B70: 46335.999 | C70: =IF(B70="","",INT(B70)-TODAY()) | D70: 682807.93 | E70: 819369.52 | F70: Andalucía | G70: Almería | I70: Presidencia del Consorcio de Residuos Sólidos del Poniente Almeriense | J70: Proyecto constructivo para la habilitación de nuevos vasos de rechazo para la planta de recuperación y compostaje de residuos sólidos urbanos de Gádor Almería: separata para impermeabilización de franja de 100m, conforme a las especificaciones y características expuestas en el presente pliego y en el proyecto técnico. | K70: 2026 1481 | L70: Abierto simplificado | M70: 5 | O70: 0.25 | P70: Criterios evaluables mediante un juicio de valor 25 (JV) | precio 65 | AMPLIACIÓN DEL PLAZO DE GARANTÍA DE LA OBRA EXIGIBLE 10 | Q70: definitiva 5% | T70: 45112000; 45261420 | U70: PCAP | V70: PPT | W70: Ver | X70: 46317
B71: 46336.5 | C71: =IF(B71="","",INT(B71)-TODAY()) | D71: 826446.28 | E71: 826446.28 | F71: Comunitat Valenciana | G71: Alicante | H71: Almoradí | I71: Junta de Gobierno del Ayuntamiento de Almoradí | J71: Renovación de firme, señalización vial y calmado del tráfico en el término municipal de Almoradí. | K71: 6799/2026 | L71: Abierto simplificado | M71: 3 | O71: 0 | P71: Mejoras 60 | Proposición Económica 40 | Q71: definitiva 5% | T71: 45233222 | U71: PCAP | W71: Ver | X71: 46317
B72: 46336.999 | C72: =IF(B72="","",INT(B72)-TODAY()) | D72: 1191405 | E72: 1191405 | F72: Andalucía | G72: Almería | I72: Junta de Gobierno de la Diputación Provincial de Almería | J72: Renovación De Calles Casco Histórico. Carboneras 85PPOS24-27BI | K72: 2025/D31000/006-013/00198 | L72: Abierto simplificado | M72: 10 | N72: E1-4; G6-4 | O72: 0.25 | P72: PRECIO 75 | OTROS 25 (JV) | Q72: definitiva 5%; complementaria 5% | T72: 45233250 | U72: PCAP | V72: PPT | W72: Ver | X72: 46317
B73: 46337.583 | C73: =IF(B73="","",INT(B73)-TODAY()) | D73: 3019728.7 | E73: 3019728.7 | F73: Andalucía | G73: Cádiz | I73: Alcaldía del Ayuntamiento de la Línea de la Concepción | J73: Obra viales en diferentes calles de La Línea de la Concepción (Cádiz) | K73: 93/26 | L73: Abierto | M73: 12 | N73: E1-4 | O73: 0.25 | P73: Compromiso ejecución de mejoras 20 | Plan de Control de Calidad de los trabajos 5 (JV) | oferta económica 30 | Análisis del proyecto base de licitación 10 (JV) | Implantación norma UNE ISO 9001 para el extendido de mezclas bituminosas en caliente: máx 4 puntos 4 | Memoria constructiva y programa de trabajos. Hasta un máximo de 10 puntos 10 (JV) | Implantación norma UNE ISO 14001 para el extendido de mezclas bituminosas en caliente: máx 3,5 puntos 3,5 | Experiencia laboral de técnico adscrito al contrato 10 | Implantación norma UNE ISO 14001 para la ejecución de obras de abastecimiento y/o saneamiento: 3,5 | Implantación norma UNE ISO 9001 para la ejecución de obras de abastecimiento y/o saneamiento: máx 4 puntos 4 | Q73: definitiva 5% | T73: 45233222; 45000000; 45230000; 45232000; 45233220; 45200000; 45233000; 45233200 | U73: PCAP | V73: PPT | W73: Ver | X73: 46314
A74: SÍ | B74: 46337.792 | C74: =IF(B74="","",INT(B74)-TODAY()) | D74: 639142.68 | E74: 692237.37 | F74: Comunitat Valenciana | G74: Alicante | H74: Alicante (Alacant) | I74: Junta de Gobierno del Ayuntamiento de Santa Pola | J74: Licitación para la contratación de las Obras de urbanización de los viales de la parcela del polígono 7.2.C de Gran Alacant (Consultorio) | K74: 21085/2026 | L74: Abierto simplificado | M74: 5 | N74: G*-3 | O74: 0.45 | P74: Precio 55 | Mejora 20 (JV) | Juicios de Valor 25 (JV) | T74: 45112500; 45211360 | U74: PCAP | V74: PPT | W74: Ver | X74: 46321
A75: SÍ | B75: 46337.999 | C75: =IF(B75="","",INT(B75)-TODAY()) | D75: 525204.12 | E75: 525204.12 | F75: Andalucía | G75: Granada | I75: Alcaldia del Ayuntamiento de Salobreña | J75: La ejecución del proyecto para la remodelación del espacio peatonal existente en el entorno del Juan ramón Jiménez | K75: Expte.5430/2026 | L75: Abierto simplificado | M75: 2.5 | N75: G6-3 | O75: 0 | P75: Oferta Económica (máximo 45 puntos) 100 | Ampliación del plazo de garantía respecto del previsto en el proyecto (hasta 30 puntos) 100 | Reducción del plazo de ejecución (en días): 0 a 25 puntos 100 | Q75: definitiva 5% | T75: 45000000; 45100000; 45233222 | U75: PCAP | V75: PPT | W75: Ver | X75: 46321
B76: 46338.5 | C76: =IF(B76="","",INT(B76)-TODAY()) | D76: 13595000 | E76: 14138800 | F76: Andalucía | G76: Sevilla | H76: Sevilla | I76: Aena. Presidencia. Consejero Delegado | J76: Renovación Del Sistema De Climatización Y Adecuación De La Protección Contra Incendios. Aeropuerto De Sevilla | K76: DIN-434/2026 | L76: Abierto | M76: 39 | O76: 0 | P76: Precio 100 | T76: 45331200 | U76: PCAP | V76: PPT | W76: Ver | X76: 46311 | Y76: 2026-10-23: plazo 2026-10-28 12:00 → 2026-11-12 12:00
A77: SÍ | B77: 46338.75 | C77: =IF(B77="","",INT(B77)-TODAY()) | D77: 1011606 | E77: 1011606 | F77: Andalucía | G77: Almería | H77: Almería | I77: Presidencia de la Autoridad Portuaria de Almería | J77: Adaptación de la infraestructura al cumplimiento de la normativa Entry/Exit System del Puerto de Almería. | K77: 34/O/AS/AL26 | L77: Abierto simplificado | M77: 6 | N77: I5-2; G4-3 | O77: 0.25 | P77: Cuantitativos 75 | Cualitativos 25 (JV) | T77: 45233222; 45314000; 45112100 | U77: PCAP | V77: PPT | W77: Ver | X77: 46321
A78: SÍ | B78: 46338.999 | C78: =IF(B78="","",INT(B78)-TODAY()) | D78: 983261.73 | E78: 983261.73 | F78: Comunitat Valenciana | G78: Alicante | I78: Junta de Gobierno del Ayuntamiento de Aspe | J78: Contrato Administrativo Obras rehabilitación de edificio de viviendas de calle Azorin y urbanizacion anexa en Aspe , Alicante conforme proyecto redactado por UTE PLAN A3 ARQUITECTURA E INGENIERIA, AKTUA MANAGEMENT Y CARMEN TORRES PEREZ | K78: 2026/46-GUACON | L78: Abierto simplificado | M78: 10 | O78: 0 | P78: PRECIO 35 | EXPERIENCIA DEL PERSONAL ADSCRITO AL CONTRATO 35 | PLAZO DE EJECUCIÓN 30 | Q78: complementaria 5%; definitiva 5% | T78: 45000000 | U78: PCAP | V78: PPT | W78: Ver | X78: 46321
A79: SÍ | B79: 46338.999 | C79: =IF(B79="","",INT(B79)-TODAY()) | D79: 859232.28 | E79: 859232.28 | F79: Andalucía | G79: Sevilla | I79: Vicepresidencia del Instituto Municipal de Deportes del Ayuntamiento de Sevilla | J79: Obras de reparación, renovación y adecuación superficial de los pavimentos de las pistas deportivas exteriores adscritas a los Centros Deportivos (CD) del Instituto Municipal de Deportes (IMD) del Ayuntamiento de Sevilla. | K79: 2026/000905 | L79: Abierto simplificado | M79: 6 | O79: 0 | P79: Ampliación del Plazo de Garantía 10 | Criterios medioambientales y de sostenibilidad 30 | OFERTA ECONOMICA 60 | Q79: definitiva 5%; complementaria 5% | T79: 45432100; 45212290; 45236119; 45212213 | U79: PCAP | V79: PPT | W79: Ver | X79: 46321
A80: SÍ | B80: 46338.999 | C80: =IF(B80="","",INT(B80)-TODAY()) | D80: 1900669.7 | E80: 1900669.7 | F80: Andalucía | G80: Cádiz | H80: Puerto Real | I80: Alcaldía del Ayuntamiento de Puerto Real | J80: B/006/2026: Ejecución de obras de recuperación integral mediante consolidación estructural del Pabellón municipal de deportes, Plan Cádiz Marcha + 2026. | K80: 13881/2026 | L80: Abierto simplificado | M80: 9 | N80: C*-4 | O80: 0 | P80: Experiencia del Jefe de obras 30 | Oferta económica 70 | Q80: definitiva 5% | R80: No | T80: 45200000; 45223210; 45261213; 45261910; 45111000; 45262400 | U80: PCAP | V80: PPT | W80: Ver | X80: 46321
A81: SÍ | B81: 46339.417 | C81: =IF(B81="","",INT(B81)-TODAY()) | D81: 538193.71 | E81: 538193.71 | F81: Andalucía | G81: Cádiz | H81: Cádiz | I81: Junta de Gobierno del Ayuntamiento de Cádiz | J81: Urbanización calle Juan de la Cierva, Dársena y Fernández Cossío, a implementar en el PAI de Cádiz, Europa transforma nuestros barrios, cofinanciado por la unión europea a través del fondo europeo de desarrollo regional FEDER en el marco del programa plurirregional de España 2021-2027 | K81: 2026/143 | L81: Abierto simplificado | M81: 5 | N81: G6-3 | O81: 0 | P81: Precio 100 | Q81: definitiva 5% | T81: 45233140; 45232400 | U81: PCAP | V81: PPT | W81: Ver | X81: 46321
A82: SÍ | B82: 46339.542 | C82: =IF(B82="","",INT(B82)-TODAY()) | D82: 900915.88 | E82: 900915.88 | F82: Comunitat Valenciana | G82: Castellón | H82: L'Alcora | I82: Alcaldía del Ayuntamiento de L'Alcora | J82: Ejecución del proyecto de obras de "Derribo y adecuación de solar de la antgua fábrica de Azulejos Sanchis de l'Alcora". | K82: 9083/2026 | L82: Abierto simplificado | M82: 4 | N82: C1-4 | O82: 0.25 | P82: Memoria técnica 25 (JV) | Aumento del plazo de garantía 10 | Precio ofertado 65 | Q82: definitiva 5% | T82: 45110000 | U82: PCAP | V82: PPT | W82: Ver | X82: 46321
B83: 46339.583 | C83: =IF(B83="","",INT(B83)-TODAY()) | D83: 3.9208795e+08 | E83: 4.3129675e+08 | F83: Comunitat Valenciana | G83: Castellón | H83: Castelló de la Plana | I83: Dirección General de Gestión Económica, Contratación e Infraestructuras de la Conselleria de Sanidad | J83: Obras del Nuevo Hospital General Universitario de Castellón. | K83: 31/2027 | L83: Abierto | M83: 60 | N83: C*-6 | O83: 0.3 | P83: PROPOSICIÓN TÉCNICA 30 (JV) | CRITERIO MAYOR EXPERIENCIA DEL EQUIPO MÍNIMO DE TRABAJO 10 | PROPOSICIÓN ECONÓMICA 50 | SEGUIMIENTO Y CONTROL DE LA OBRA MEDIANTE NUEVAS TECNOLOGÍAS 5 | INCREMENTO PLAZO DE GARANTÍA 5 | Q83: complementaria 5%; definitiva 5% | R83: Recogida en el apartado H del Anexo I al PCAP. | T83: 45215100 | U83: PCAP | V83: PPT | W83: Ver | X83: 46310 | Y83: 2026-10-20: plazo 2026-11-03 14:00 → 2026-11-13 14:00
B84: 46340.999 | C84: =IF(B84="","",INT(B84)-TODAY()) | D84: 3796334.3 | E84: 3796334.3 | F84: Andalucía | G84: Málaga | H84: Coín | I84: Alcaldía del Ayuntamiento de Coín | J84: Contrato de las obras de construcción de un puente sobre el rio Pereilas T.M. de Coín, Málaga, financiado con cargo a las ayudas de la Administración General del Estado a través del Ministerio de Política Territorial y Memoria Democrática previstas en el artículo 7 del Real Decreto-Ley 5/2026 de 17 de febrero. | K84: 4835/2026 | L84: Abierto | M84: 18 | N84: B*-5 | O84: 0.25 | P84: Análisis del Proyecto base de licitación 10 (JV) | Importe ofertado para ejecutar las obras 10 | Memoria Constructiva e Impacto de las Obras 15 (JV) | Plazo de ejecución 45 | Incremento de la duración del plazo de garantía 20 | Q84: definitiva 5% | T84: 45221110; 45233222 | U84: PCAP | V84: PPT | W84: Ver | X84: 46315
B85: 46342.583 | C85: =IF(B85="","",INT(B85)-TODAY()) | D85: 3884750.5 | E85: 3884750.5 | F85: Andalucía | G85: Córdoba | H85: Córdoba | I85: Viviendas Municipales de Córdoba SA | J85: El objeto del contrato es la construcción de 30 viviendas protegidas con trasteros y plazas de aparcamiento en régimen de venta. | K85: 3-O/2026 | L85: Abierto | M85: 20 | N85: C*-4 | O85: 0 | P85: Oferta económica 66 | Plazo de ejecución 2 | Plazo de garantía 10 | Ampliación del plan de control de calidad 10 | Experiencia del jefe de obra y del encargado en ejecución de obras 12 | Q85: complementaria 5%; definitiva 5% | T85: 45211340; 45211341 | U85: PCAP | V85: PPT | W85: Ver | X85: 46314
B86: 46342.583 | C86: =IF(B86="","",INT(B86)-TODAY()) | D86: 4299512.5 | E86: 4299512.5 | F86: Andalucía | G86: Córdoba | I86: Viviendas Municipales de Córdoba SA | J86: Obras con suministro de materiales por ajuste o a tanto alzado y con gestión a riesgo y ventura del contratista para la construcción de dos promociones de 15 viviendas protegidas cada una en régimen de venta, trasteros y plazas de aparcamiento en las parcelas R1 y R2 del PP SRA-SUR del PGOU de córdoba. | K86: 2-O/2026 | L86: Abierto | M86: 24 | N86: C*-4 | O86: 0 | P86: Ampliación del Plan de control de calidad 10 | Plazo de garantía 10 | Precio Oferta Integradora - Lotes 1_2 0 | Oferta económica 66 | Plazo de ejecución 2 | Experiencia del jefe de obra y del encargado en ejecución de obras 12 | Q86: definitiva 5% | S86: 2 | T86: 45211340 | U86: PCAP | V86: PPT | W86: Ver | X86: 46314
B87: 46342.999 | C87: =IF(B87="","",INT(B87)-TODAY()) | D87: 2470745 | E87: 2470745 | F87: Comunitat Valenciana | G87: Valencia | I87: Pleno del Ayuntamiento de Puçol | J87: Reforma del Colegio Jaume I de Puçol y construcción de un gimnasio y un aulario para educación infantil (EDIFICANT) | K87: 2138082J | L87: Abierto | M87: 12 | N87: C9-4 | O87: 0.26 | P87: 6) Propuesta ejecución de partidas edificio existente antes vacaciones de verano 6 (JV) | 5) Propuesta organización del solapamiento entre la obra y la actividad docente 6 (JV) | 2) Reducción del plazo parcial de ejecución de la reforma interior del edificio existente 15 | 7) Programación de los trabajos 8 (JV) | 1) Oferta económica 35 | 4) Propuesta de organización y estudio del entorno de la obra 6 (JV) | 3) Mejoras 24 | Q87: definitiva 5% | T87: 45200000; 45214200 | U87: PCAP | W87: Ver | X87: 46314
B88: 46342.999 | C88: =IF(B88="","",INT(B88)-TODAY()) | D88: 3900977.9 | E88: 5071271.2 | F88: Comunitat Valenciana | G88: Valencia | I88: Consorcio Hospital General Universitario de Valencia | J88: Obra de reforma de la cocina del Consorcio Hospital General Universitario de Valencia. | K88: CMAYOR/2027/HGUV0/0088 | L88: Abierto | M88: 12 | O88: 0.23 | P88: CRITERIOS SUBJETIVOS 23 (JV) | RESTO DE CRITERIOS OBJETIVOS 27 | IMPORTE DE LA OFERTA 50 | Q88: definitiva 5%; complementaria 5% | T88: 45215100; 39141400; 45421151; 45215140; 45212500; 45215120 | U88: PCAP | V88: PPT | W88: Ver | X88: 46314
B89: 46342.999 | C89: =IF(B89="","",INT(B89)-TODAY()) | D89: 1332042.2 | E89: 1332042.2 | F89: Comunitat Valenciana | G89: Valencia | I89: Alcaldía del Ayuntamiento de Manises | J89: Obras para la ejecución de las actuaciones incluidas en el plan edificant correspondientes a la fase 2 del CEIP Enric Valor ya la adecuación y mejora del CEIP José Garcia Planells | K89: 2754824W | L89: Abierto | M89: 6 | N89: J2-3; C4-3; I9-3; C6-3 | O89: 0.3 | P89: Oferta económica 40 | Ampliación del plazo de garantía 10 | Memoria de organización 30 (JV) | Disposición de jefe de obra 20 | S89: 2 | T89: 45214200; 45200000; 45300000; 45261410; 45331200 | U89: PCAP | V89: PPT | W89: Ver | X89: 46317
B90: 46342.999 | C90: =IF(B90="","",INT(B90)-TODAY()) | D90: 3636363.6 | E90: 3636363.6 | F90: Andalucía | G90: Almería | I90: Junta de Gobierno de la Diputación Provincial de Almería | J90: Gran Eco-bulevard Vera - Palomares. Este Proyecto Podrá Ser Cofinanciado Por La Unión Europea A Través Del Fondo Europeo De Desarrollo Regional (feder) En El Marco Del Programa Plurirregional De Españ 9PAI-LEVANTE30 | K90: 2026/D31000/006-002/00004 | L90: Abierto | M90: 12.2 | N90: I1-4; G6-4 | O90: 0.25 | P90: Precio 75 | Oferta Técnica 25 (JV) | Q90: complementaria 5%; definitiva 5% | T90: 45111291 | U90: PCAP | V90: PPT | W90: Ver | X90: 46317
B91: 46342.999 | C91: =IF(B91="","",INT(B91)-TODAY()) | D91: 661157.03 | E91: 661157.03 | F91: Andalucía | G91: Córdoba | I91: Junta de Gobierno de la Diputación Provincial de Córdoba | J91: Obras de mejora del acceso a Priego de Córdoba, en un tramo de 1,64 Km semiurbanizados de la CO-8209 "de Priego de Córdoba a Luque por Fuente Alhama (Priego de Córdoba), Córdoba | K91: 776/26 | L91: Abierto | M91: 6 | N91: G4-3 | O91: 0.4 | P91: Oferta económica respecto al presupuesto base de licitación 60 | Justificación del aumento de calidad en el proceso de ejecución 10 (JV) | Programa de trabajo con valoración mensual y acumulada a precios de proyecto 10 (JV) | Memoria descriptiva sobre el conocimiento del estado actual del tramo de obra y del proyecto 20 (JV) | Q91: complementaria 5%; definitiva 5% | T91: 45233000 | U91: PCAP | V91: PPT | W91: Ver | X91: 46317
B92: 46344.999 | C92: =IF(B92="","",INT(B92)-TODAY()) | D92: 1494349.1 | E92: 1494349.1 | F92: Comunitat Valenciana | G92: Valencia | H92: Yátova | I92: Pleno del Ayuntamiento de Yátova | J92: Reparación, acondicionamiento y mejora de caminos rurales en el término municipal de Yátova. Subvención Ministerio Dana2024 | K92: 899/2026 | L92: Abierto simplificado | M92: 6 | N92: G*-4 | O92: 0 | P92: Experiencia obras similiares 30 | Reconocimiento del lugar 20 | Mayor baja económica 30 | Ampliación del plazo de garantía 20 | Q92: definitiva 5% | T92: 45233250; 45233222; 45233251; 45233140 | U92: PCAP | V92: PPT | W92: Ver | X92: 46317
A93: SÍ | B93: 46344.999 | C93: =IF(B93="","",INT(B93)-TODAY()) | D93: 2520482.6 | E93: 2520482.6 | F93: Andalucía | G93: Málaga | I93: Concejalía de Hacienda del Ayuntamiento de Benalmádena | J93: Plan de Asfaltado 2024 del T.M. de Benalmádena | K93: 2026/60664M | L93: Abierto | M93: 5 | N93: G4-5 | O93: 0 | P93: Económico 70 | Plazo de ejecución 6 | Actuaciones sin coste para la Administración 24 | Q93: definitiva 5% | R93: No aplica, conforme Anexo 1 letra J) del PCAP | T93: 45233252 | U93: PCAP | W93: Ver | X93: 46321
A94: SÍ | B94: 46344.999 | C94: =IF(B94="","",INT(B94)-TODAY()) | D94: 2292565.9 | E94: 2292565.9 | F94: Comunitat Valenciana | G94: Valencia | I94: Pleno del Ayuntamiento de Carlet | J94: Obras de restitución de la red de saneamiento y pluviales del barrio del Cortijo y reposición de pluviales en la calle Rafael Peris, financiadas con cargo al Fondo de Solidaridad de la Unión Europea | K94: 3126/2026 | L94: Abierto | M94: 9 | N94: E*-4 | O94: 0 | P94: Ampliación del plazo de garantía 10 | Oferta económica 70 | Uso de materiales con menor huella de carbono 20 | Q94: definitiva 5% | T94: 45240000; 45232440; 45233200; 45232150 | U94: PCAP | V94: PPT | W94: Ver | X94: 46321
A95: SÍ | B95: 46344.999 | C95: =IF(B95="","",INT(B95)-TODAY()) | D95: 782875 | E95: 782875 | F95: Andalucía | G95: Sevilla | I95: Alcaldía del Ayuntamiento de Lantejuela | J95: Obras de actuciones de reforma en el complejo polideportivo municipal de lantejuela (Sevilla) | K95: P4105200B-2026/000230-PAA | L95: Abierto | M95: 6 | O95: 0 | P95: Aspecto Económico (precio) [1] 100 | S95: 2 | T95: 45200000; 45212200 | U95: PCAP | V95: PPT | W95: Ver | X95: 46321
A96: SÍ | B96: 46345.583 | C96: =IF(B96="","",INT(B96)-TODAY()) | D96: 2070399.7 | E96: 2070399.7 | F96: Comunitat Valenciana | G96: Valencia | I96: Concejalía Delegada de Contratación del Ayuntamiento de Gandía | J96: Contrato de obras consistente en la ejecución del proyecto actualizado de actuaciones en el CEIP Mondúber, derivado de la modificación de la delegación de competencias_ EDIFICANT. | K96: CONT-074/2026 (50124/2026) | L96: Abierto | M96: 14 | N96: C*-5 | O96: 0.25 | P96: Metodología y programación 15 (JV) | Incorporación de mejoras 27 | Oferta económica 40 | Conocimiento del proyecto 10 (JV) | Ampliación plazo de garantía 8 | T96: 45214210 | U96: PCAP | V96: PPT | W96: Ver | X96: 46321
B97: 46346.999 | C97: =IF(B97="","",INT(B97)-TODAY()) | D97: 8318780.9 | E97: 8318780.9 | F97: Andalucía | G97: Sevilla | I97: Junta de Gobierno del Ayuntamiento de Carmona | J97: Obras para la ejecución del complejo de la música y el patrimonio en los antiguos mataderos de Carmona y la adecuación de sus entornos. | K97: EXP 25-173-22 | L97: Abierto | M97: 20 | N97: C*-5 | O97: 0.45 | P97: B.2. Ampliación Plazo de Garantía. 10 | A.1. Criterio de Estudio Técnico Detallado: 20 (JV) | B.3. Sistemas de gestión certificados. 10 | A.3. Criterio de Ambiental. 5 (JV) | B.5 Implementación de sistema de seguimiento de obra con cámara fotográfica. 5 | A.2. Criterio de Estudio Técnico Detallado: Programación de los trabajos. 20 (JV) | B.4 Implementación de Tecnología Building Information Modeling (BIM) 10 | B.1. Oferta Económica 20 | Q97: definitiva 5% | T97: 45000000; 45212300; 45213230; 45112700; 45212321; 45454100 | U97: PCAP | V97: PPT | W97: Ver | X97: 46311
B98: 46350.458 | C98: =IF(B98="","",INT(B98)-TODAY()) | D98: 3246355.9 | E98: 3246355.9 | F98: Andalucía | G98: Sevilla | I98: Comisión Ejecutiva de la Gerencia de Urbanismo de Sevilla | J98: Obras del Proyecto básico y de ejecución para rehabilitación, consolidación y puesta en valor de la sala de Profundis y las viviendas anexas del Real Monasterio de Santa Clara. | K98: 19/2026 | L98: Abierto | M98: 18 | N98: K7-4 | O98: 0 | P98: 1. OFERTA ECONÓMICA 20 | 2. MAYOR CUALIFICACIÓN Y EXPERIENCIA DEL EQUIPO TÉCNICO. SUBCRITERIO D. BAREMACIÓN DEL PERFIL 4 RESTAURADOR. 10 | 3. AMPLIACIÓN DEL PLAZO DE GARANTÍA. 30 | 2. MAYOR CUALIFICACIÓN Y EXPERIENCIA DEL EQUIPO TÉCNICO. SUBCRITERIO B. BAREMACIÓN DEL PERFIL 2. ENCARGADO. 15 | 2. MAYOR CUALIFICACIÓN Y EXPERIENCIA DEL EQUIPO TÉCNICO. SUBCRITERIO C. BAREMACIÓN DEL PERFIL 3. TÉCNICO EN PREVENCIÓN DE RIESGOS LABORALES. 10 | 2. MAYOR CUALIFICACIÓN Y EXPERIENCIA DEL EQUIPO TÉCNICO. SUBCRITERIO A. BAREMACIÓN DEL PERFIL 1. TÉCNICO JEFE DE OBRA. 15 | Q98: definitiva 5%; complementaria 5% | R98: FÓRMULA 831. Obras de restauración de edificios. | T98: 45212300 | U98: PCAP | W98: Ver | X98: 46310
A99: SÍ | B99: 46350.542 | C99: =IF(B99="","",INT(B99)-TODAY()) | D99: 22148579 | E99: 26338629 | F99: Andalucía | G99: Málaga | I99: Junta de Gobierno del Ayuntamiento de Málaga | J99: Redacción del proyecto constructivo y ejecución de las obras del soterramiento de la Avenida de Valle-Inclán en la intersección con el Camino de Suárez, la Calle Martínez de la Rosa y el acceso a las barriadas de Carlinda, La Corta y San Alberto, en la ciudad de Málaga | K99: 31/26 | L99: Abierto | M99: 31 | N99: B2-6; G6-3 | O99: 0.49 | P99: Calidad del Equipo Técnico 20 | Adaptación de espacios aportados por el Ayuntamiento destinados a aparcamientos provisionales para los vecinos durante la ejecución de las obrasobras, por un importe máximo de 150.000€ 2 | Oferta Económica Proyecto Construcción 5 | Oferta Económica Ejecución de las Obras 24 | Propuesta Técnica 49 (JV) | Q99: definitiva 5% | R99: RD 1359/2011, Anexo II, Fórmula 111. Estructuras de hormigón armado y pretensado | T99: 45221000; 71300000 | U99: PCAP | V99: PPT | W99: Ver | X99: 46321
A100: SÍ | B100: 46351.542 | C100: =IF(B100="","",INT(B100)-TODAY()) | D100: 15485879 | E100: 20131642 | F100: Comunitat Valenciana | G100: Valencia | H100: Valencia | I100: Consejo de Administración de la Autoridad Portuaria de Valencia | J100: Construcción de nueva subestación transformadora de 132/20 kV tipo GIS de interior con dos transformadores 132/20 kV, 55 MVA-ST. Autoridad Portuaria de Valencia 2 | K100: EC26-C02-02310 | L100: Abierto | M100: 20 | N100: I4-4 | O100: 0.49 | P100: Criterios evaluables mediante juicio de valor 49 (JV) | Oferta económica 51 | Q100: definitiva 5%; complementaria 5% | T100: 45232220 | U100: PCAP | V100: PPT | W100: Ver | X100: 46321
...

Sheet Resumen
A1: Licitaciones de obras en plazo · Resumen
A3: Actualizado | B3: 46321.287
A4: Ámbito (códigos NUTS) | B4: ES52, ES61
A5: Rango de presupuesto base sin IVA | B5: entre 500.000,00 € y ∞
A6: Fuentes leídas | B6: 0 fichero(s) mensual(es) + 14 página(s) del feed
A7: Entradas leídas | B7: 6555
A8: Periodo cubierto en esta lectura | B8: 21/10/2026 – 25/10/2026
A9: Licitaciones en la base | B9: 2050
A10: En plazo | B10: =COUNTA('En plazo'!$J$2:$J$102)
A11: Importe total en plazo | B11: =SUM('En plazo'!$D$2:$D$102)
A12: Nuevas desde la ejecución anterior | B12: =COUNTIF('En plazo'!$A$2:$A$102,"SÍ")
A13: Con cambios registrados | B13: =COUNTIF('En plazo'!$Y$2:$Y$102,"?*")
A14: Vencen en 7 días o menos | B14: =COUNTIFS('En plazo'!$C$2:$C$102,">=0",'En plazo'!$C$2:$C$102,"<=7")
A16: Por comunidad y provincia
A17: Comunidad | B17: Provincia | C17: Nº en plazo | D17: Importe | E17: Nuevas | F17: Vencen ≤ 7 días
A18: Andalucía | B18: Almería | C18: =COUNTIFS('En plazo'!$F$2:$F$102,"Andalucía",'En plazo'!$G$2:$G$102,"Almería") | D18: =SUMIFS('En plazo'!$D$2:$D$102,'En plazo'!$F$2:$F$102,"Andalucía",'En plazo'!$G$2:$G$102,"Almería") | E18: =COUNTIFS('En plazo'!$F$2:$F$102,"Andalucía",'En plazo'!$G$2:$G$102,"Almería",'En plazo'!$A$2:$A$102,"SÍ") | F18: =COUNTIFS('En plazo'!$F$2:$F$102,"Andalucía",'En plazo'!$G$2:$G$102,"Almería",'En plazo'!$C$2:$C$102,">=0",'En plazo'!$C$2:$C$102,"<=7")
A19: Andalucía | B19: Cádiz | C19: =COUNTIFS('En plazo'!$F$2:$F$102,"Andalucía",'En plazo'!$G$2:$G$102,"Cádiz") | D19: =SUMIFS('En plazo'!$D$2:$D$102,'En plazo'!$F$2:$F$102,"Andalucía",'En plazo'!$G$2:$G$102,"Cádiz") | E19: =COUNTIFS('En plazo'!$F$2:$F$102,"Andalucía",'En plazo'!$G$2:$G$102,"Cádiz",'En plazo'!$A$2:$A$102,"SÍ") | F19: =COUNTIFS('En plazo'!$F$2:$F$102,"Andalucía",'En plazo'!$G$2:$G$102,"Cádiz",'En plazo'!$C$2:$C$102,">=0",'En plazo'!$C$2:$C$102,"<=7")
A20: Andalucía | B20: Córdoba | C20: =COUNTIFS('En plazo'!$F$2:$F$102,"Andalucía",'En plazo'!$G$2:$G$102,"Córdoba") | D20: =SUMIFS('En plazo'!$D$2:$D$102,'En plazo'!$F$2:$F$102,"Andalucía",'En plazo'!$G$2:$G$102,"Córdoba") | E20: =COUNTIFS('En plazo'!$F$2:$F$102,"Andalucía",'En plazo'!$G$2:$G$102,"Córdoba",'En plazo'!$A$2:$A$102,"SÍ") | F20: =COUNTIFS('En plazo'!$F$2:$F$102,"Andalucía",'En plazo'!$G$2:$G$102,"Córdoba",'En plazo'!$C$2:$C$102,">=0",'En plazo'!$C$2:$C$102,"<=7")
A21: Andalucía | B21: Granada | C21: =COUNTIFS('En plazo'!$F$2:$F$102,"Andalucía",'En plazo'!$G$2:$G$102,"Granada") | D21: =SUMIFS('En plazo'!$D$2:$D$102,'En plazo'!$F$2:$F$102,"Andalucía",'En plazo'!$G$2:$G$102,"Granada") | E21: =COUNTIFS('En plazo'!$F$2:$F$102,"Andalucía",'En plazo'!$G$2:$G$102,"Granada",'En plazo'!$A$2:$A$102,"SÍ") | F21: =COUNTIFS('En plazo'!$F$2:$F$102,"Andalucía",'En plazo'!$G$2:$G$102,"Granada",'En plazo'!$C$2:$C$102,">=0",'En plazo'!$C$2:$C$102,"<=7")
A22: Andalucía | B22: Huelva | C22: =COUNTIFS('En plazo'!$F$2:$F$102,"Andalucía",'En plazo'!$G$2:$G$102,"Huelva") | D22: =SUMIFS('En plazo'!$D$2:$D$102,'En plazo'!$F$2:$F$102,"Andalucía",'En plazo'!$G$2:$G$102,"Huelva") | E22: =COUNTIFS('En plazo'!$F$2:$F$102,"Andalucía",'En plazo'!$G$2:$G$102,"Huelva",'En plazo'!$A$2:$A$102,"SÍ") | F22: =COUNTIFS('En plazo'!$F$2:$F$102,"Andalucía",'En plazo'!$G$2:$G$102,"Huelva",'En plazo'!$C$2:$C$102,">=0",'En plazo'!$C$2:$C$102,"<=7")
A23: Andalucía | B23: Jaén | C23: =COUNTIFS('En plazo'!$F$2:$F$102,"Andalucía",'En plazo'!$G$2:$G$102,"Jaén") | D23: =SUMIFS('En plazo'!$D$2:$D$102,'En plazo'!$F$2:$F$102,"Andalucía",'En plazo'!$G$2:$G$102,"Jaén") | E23: =COUNTIFS('En plazo'!$F$2:$F$102,"Andalucía",'En plazo'!$G$2:$G$102,"Jaén",'En plazo'!$A$2:$A$102,"SÍ") | F23: =COUNTIFS('En plazo'!$F$2:$F$102,"Andalucía",'En plazo'!$G$2:$G$102,"Jaén",'En plazo'!$C$2:$C$102,">=0",'En plazo'!$C$2:$C$102,"<=7")
A24: Andalucía | B24: Málaga | C24: =COUNTIFS('En plazo'!$F$2:$F$102,"Andalucía",'En plazo'!$G$2:$G$102,"Málaga") | D24: =SUMIFS('En plazo'!$D$2:$D$102,'En plazo'!$F$2:$F$102,"Andalucía",'En plazo'!$G$2:$G$102,"Málaga") | E24: =COUNTIFS('En plazo'!$F$2:$F$102,"Andalucía",'En plazo'!$G$2:$G$102,"Málaga",'En plazo'!$A$2:$A$102,"SÍ") | F24: =COUNTIFS('En plazo'!$F$2:$F$102,"Andalucía",'En plazo'!$G$2:$G$102,"Málaga",'En plazo'!$C$2:$C$102,">=0",'En plazo'!$C$2:$C$102,"<=7")
A25: Andalucía | B25: Sevilla | C25: =COUNTIFS('En plazo'!$F$2:$F$102,"Andalucía",'En plazo'!$G$2:$G$102,"Sevilla") | D25: =SUMIFS('En plazo'!$D$2:$D$102,'En plazo'!$F$2:$F$102,"Andalucía",'En plazo'!$G$2:$G$102,"Sevilla") | E25: =COUNTIFS('En plazo'!$F$2:$F$102,"Andalucía",'En plazo'!$G$2:$G$102,"Sevilla",'En plazo'!$A$2:$A$102,"SÍ") | F25: =COUNTIFS('En plazo'!$F$2:$F$102,"Andalucía",'En plazo'!$G$2:$G$102,"Sevilla",'En plazo'!$C$2:$C$102,">=0",'En plazo'!$C$2:$C$102,"<=7")
A26: Comunitat Valenciana | B26: (sin provincia) | C26: =COUNTIFS('En plazo'!$F$2:$F$102,"Comunitat Valenciana",'En plazo'!$G$2:$G$102,"") | D26: =SUMIFS('En plazo'!$D$2:$D$102,'En plazo'!$F$2:$F$102,"Comunitat Valenciana",'En plazo'!$G$2:$G$102,"") | E26: =COUNTIFS('En plazo'!$F$2:$F$102,"Comunitat Valenciana",'En plazo'!$G$2:$G$102,"",'En plazo'!$A$2:$A$102,"SÍ") | F26: =COUNTIFS('En plazo'!$F$2:$F$102,"Comunitat Valenciana",'En plazo'!$G$2:$G$102,"",'En plazo'!$C$2:$C$102,">=0",'En plazo'!$C$2:$C$102,"<=7")
A27: Comunitat Valenciana | B27: Alicante | C27: =COUNTIFS('En plazo'!$F$2:$F$102,"Comunitat Valenciana",'En plazo'!$G$2:$G$102,"Alicante") | D27: =SUMIFS('En plazo'!$D$2:$D$102,'En plazo'!$F$2:$F$102,"Comunitat Valenciana",'En plazo'!$G$2:$G$102,"Alicante") | E27: =COUNTIFS('En plazo'!$F$2:$F$102,"Comunitat Valenciana",'En plazo'!$G$2:$G$102,"Alicante",'En plazo'!$A$2:$A$102,"SÍ") | F27: =COUNTIFS('En plazo'!$F$2:$F$102,"Comunitat Valenciana",'En plazo'!$G$2:$G$102,"Alicante",'En plazo'!$C$2:$C$102,">=0",'En plazo'!$C$2:$C$102,"<=7")
A28: Comunitat Valenciana | B28: Castellón | C28: =COUNTIFS('En plazo'!$F$2:$F$102,"Comunitat Valenciana",'En plazo'!$G$2:$G$102,"Castellón") | D28: =SUMIFS('En plazo'!$D$2:$D$102,'En plazo'!$F$2:$F$102,"Comunitat Valenciana",'En plazo'!$G$2:$G$102,"Castellón") | E28: =COUNTIFS('En plazo'!$F$2:$F$102,"Comunitat Valenciana",'En plazo'!$G$2:$G$102,"Castellón",'En plazo'!$A$2:$A$102,"SÍ") | F28: =COUNTIFS('En plazo'!$F$2:$F$102,"Comunitat Valenciana",'En plazo'!$G$2:$G$102,"Castellón",'En plazo'!$C$2:$C$102,">=0",'En plazo'!$C$2:$C$102,"<=7")
A29: Comunitat Valenciana | B29: Valencia | C29: =COUNTIFS('En plazo'!$F$2:$F$102,"Comunitat Valenciana",'En plazo'!$G$2:$G$102,"Valencia") | D29: =SUMIFS('En plazo'!$D$2:$D$102,'En plazo'!$F$2:$F$102,"Comunitat Valenciana",'En plazo'!$G$2:$G$102,"Valencia") | E29: =COUNTIFS('En plazo'!$F$2:$F$102,"Comunitat Valenciana",'En plazo'!$G$2:$G$102,"Valencia",'En plazo'!$A$2:$A$102,"SÍ") | F29: =COUNTIFS('En plazo'!$F$2:$F$102,"Comunitat Valenciana",'En plazo'!$G$2:$G$102,"Valencia",'En plazo'!$C$2:$C$102,">=0",'En plazo'!$C$2:$C$102,"<=7")
A30: Total | C30: =SUM(C18:C29) | D30: =SUM(D18:D29) | E30: =SUM(E18:E29) | F30: =SUM(F18:F29)
A32: Fuente: Plataforma de Contratación del Sector Público (feed ATOM licitacionesPerfilesContratanteCompleto3) y ficheros mensuales de datos abiertos del Ministerio de Hacienda.
A33: Los días restantes y los vencimientos se recalculan con la fecha del día al abrir el libro.
A34: Plazo de ejecución en meses: los plazos en días se dividen entre 30 y los de años se multiplican por 12.
A35: Este libro se regenera en cada ejecución: las anotaciones que se hagan en él se pierden. Para el seguimiento, copiar las filas al libro de preselección.

Sheet Histórico
A1: Estado | B1: Fecha límite | C1: Presupuesto base sin IVA | D1: Valor estimado | E1: Comunidad | F1: Provincia | G1: Municipio | H1: Órgano de contratación | I1: Objeto | J1: Expediente | K1: Procedimiento | L1: Plazo de ejecución (meses) | M1: Clasificación exigida | N1: Juicio de valor | O1: Nº lotes | P1: CPV | Q1: Ficha PLACSP | R1: PCAP | S1: Primera detección | T1: Última actualización en PLACSP | U1: Cambios
A2: En plazo | B2: 46335.583 | C2: 65084.97 | D2: 65084.97 | E2: Andalucía | F2: Huelva | G2: santa bárbara de casa | H2: Alcaldía del Ayuntamiento de Santa Bárbara de Casa | I2: contrato de obras de urbanización mediante obras ordinarias | J2: 480.1/2026 | K2: Abierto simplificado | L2: 3 | N2: 0 | P2: 45233252 | Q2: Ver | S2: 46321 | T2: 46320.807
A3: En plazo | B3: 46351.542 | C3: 15485879 | D3: 20131642 | E3: Comunitat Valenciana | F3: Valencia | G3: Valencia | H3: Consejo de Administración de la Autoridad Portuaria de Valencia | I3: Construcción de nueva subestación transformadora de 132/20 kV tipo GIS de interior con dos transformadores 132/20 kV, 55 MVA-ST. Autoridad Portuaria de Valencia 2 | J3: EC26-C02-02310 | K3: Abierto | L3: 20 | M3: I4-4 | N3: 0.49 | P3: 45232220 | Q3: Ver | R3: PCAP | S3: 46321 | T3: 46320.436
A4: Resuelta | B4: 46220.999 | C4: 5985824.8 | D4: 5985824.8 | E4: Andalucía | F4: Málaga | H4: Pleno del Ayuntamiento de Alhaurín de la Torre | I4: Obras para la construcción del aparcamiento subterráneo disuasorio en la Avenida Isaac Peral y la reurbanización y peatonalización parcial de la Avenida Isaac Peral en el T.M. Alhaurín de la Torre. | J4: 2026 CONT-00019 | K4: Abierto | L4: 30 | M4: C2-4 | N4: 0 | P4: 45200000; 45340000; 45261000; 45440000; 45320000; 45213316; 45330000; 45420000 | Q4: Ver | R4: PCAP | S4: 46321 | T4: 46320.31
A5: Resuelta | B5: 46294.999 | C5: 29981.19 | D5: 32979.31 | E5: Comunitat Valenciana | F5: Castellón | G5: Castelló de la Plana | H5: Dirección Económica del Consorcio Hospitalario Provincial de Castellón | I5: CMAYOR/2026/HPC00/0737 OBRAS de renovación y adaptación de tres aseos existentes en la planta baja del Consorcio Hospitalario Provincial Universitario de Castellón, ubicados en los bloques A (Consultas Externas), C (Área de Rehabilitación) y D (Área de Oncología), incorporando en cada uno de ellos equipamiento higiénico específico para personas ostomizadas | J5: CMAYOR/2026/HPC00/0737 | K5: Abierto simplificado | L5: 2 | N5: 0 | P5: 45000000; 45215140 | Q5: Ver | R5: PCAP | S5: 46311 | T5: 46319.802 | U5: 2026-10-26: estado ADJ → RES
A6: En plazo | B6: 46335.999 | C6: 41322.31 | D6: 41322.31 | E6: Andalucía | F6: Sevilla | H6: Alcaldia del Ayuntamiento de Marinaleda | I6: Reparación de Caminos Rurales (Línea de Subvenciones Borrasca NELSON) | J6: P4106100C-2026/000108-PAAB | K6: Abierto simplificado | L6: 3 | N6: 0 | P6: 45233142 | Q6: Ver | R6: PCAP | S6: 46321 | T6: 46319.539
A7: En plazo | B7: 46335.999 | C7: 45409.09 | D7: 45409.09 | E7: Andalucía | F7: Sevilla | H7: Alcaldia del Ayuntamiento de Marinaleda | I7: Mejora de Caminos Rurales de Marinaleda (Sevilla) | J7: P4106100C-2026/000107-PAAB | K7: Abierto simplificado | L7: 3 | N7: 0 | P7: 45233142 | Q7: Ver | R7: PCAP | S7: 46321 | T7: 46319.536
A8: En plazo | B8: 46332.542 | C8: 55300.65 | D8: 55300.65 | E8: Andalucía | F8: Huelva | G8: SANTA BARBARA DE CASA | H8: Alcaldía del Ayuntamiento de Santa Bárbara de Casa | I8: contrato de obras de mejora de la calle Noria en Santa Bárbara de Casa | J8: 480/2026 | K8: Abierto simplificado | L8: 3 | N8: 0 | P8: 45233252 | Q8: Ver | S8: 46317 | T8: 46319.525
A9: En plazo | B9: 46335.999 | C9: 27389.04 | D9: 27389.04 | E9: Andalucía | F9: Huelva | G9: PAYMOGO | H9: Alcaldía del Ayuntamiento de Paymogo | I9: Constituye el objeto del contrato la ejecución de las obras de reparación del firme del Camino de Las Peñuelas, de Paymogo (Huelva), de titularidad municipal, con referencia catastral 21057A009090040000LO | J9: 493/2026 | K9: Abierto simplificado | L9: 1 | N9: 0 | P9: 45233160 | Q9: Ver | R9: PCAP | S9: 46321 | T9: 46318.842
A10: En plazo | B10: 46338.999 | C10: 175462.98 | D10: 175462.98 | E10: Comunitat Valenciana | F10: Valencia | H10: Alcaldía del Ayuntamiento de Moixent | I10: Consolidación de la torre sur del Castillo de Moixent, Fase I | J10: 1615/2026 | K10: Abierto simplificado | L10: 4 | N10: 0.12 | P10: 45212314; 45454100; 45262512; 45212350 | Q10: Ver | R10: PCAP | S10: 46321 | T10: 46318.72
A11: En plazo | B11: 46338.999 | C11: 328657.46 | D11: 328657.46 | E11: Andalucía | F11: Sevilla | G11: Écija | H11: Junta de Gobierno del Ayuntamiento de Ecija | I11: Obras Rehabilitación y Puesta en uso de Salas junto a Patio de las Yeguas del Palacio Marqueses de Peñaflor, por procedimiento abierto simplificado,tramitación ordinaria, financiado con cargo al 2% Cultural del Ministerio deTransportes, Movilidad y Agenda Urbana para conservación o enriquecimiento de bienes inmuebles del Patrimonio Histórico Español. | J11: 16242/2025 | K11: Abierto simplificado | L11: 6 | N11: 0 | P11: 45212350 | Q11: Ver | R11: PCAP | S11: 46321 | T11: 46318.717
A12: En plazo | B12: 46350.542 | C12: 22148579 | D12: 26338629 | E12: Andalucía | F12: Málaga | H12: Junta de Gobierno del Ayuntamiento de Málaga | I12: Redacción del proyecto constructivo y ejecución de las obras del soterramiento de la Avenida de Valle-Inclán en la intersección con el Camino de Suárez, la Calle Martínez de la Rosa y el acceso a las barriadas de Carlinda, La Corta y San Alberto, en la ciudad de Málaga | J12: 31/26 | K12: Abierto | L12: 31 | M12: B2-6; G6-3 | N12: 0.49 | P12: 45221000; 71300000 | Q12: Ver | R12: PCAP | S12: 46321 | T12: 46318.681
A13: Resuelta | B13: 46216.999 | C13: 156579.12 | D13: 156579.12 | E13: Comunitat Valenciana | F13: Valencia | H13: Junta de Gobierno del Ayuntamiento de Alboraya | I13: Obras de reforma del antiguo polideportivo de Alboraya | J13: 704/2026 | K13: Abierto simplificado | L13: 4 | N13: 0 | P13: 45212290 | Q13: Ver | R13: PCAP | S13: 46321 | T13: 46318.656
A14: Adjudicada | B14: 46259.999 | C14: 111113.32 | D14: 111113.32 | E14: Andalucía | F14: Córdoba | H14: Alcaldía del Ayuntamiento de Rute | I14: Ejecución del Proyecto de Arreglo de la Pista Deportiva en CEIP Ruperto Fernandez Tenllado (Córdoba) | J14: 2830_26 OBRAS PISTA POLID CEIP RUPERTO FDEZ | K14: Abierto simplificado | L14: 2.5 | N14: 0 | P14: 45212220; 45200000 | Q14: Ver | R14: PCAP | S14: 46310 | T14: 46318.63 | U14: 2026-10-26: estado EV → ADJ
A15: Adjudicada | B15: 46295.999 | C15: 165448.79 | D15: 165448.79 | E15: Andalucía | F15: Córdoba | G15: ALDEA DE NACIMIENTO DE ZAMBRA | H15: Alcaldía del Ayuntamiento de Rute | I15: Ejecución del Proyecto de Reparación y Adecentamiento de la pista polideportiva de la Aldea de Nacimiento de Zambra de Rute | J15: 3862_26 OBRAS PISTAS NAC ZAMBRA | K15: Abierto simplificado | L15: 4 | N15: 0 | P15: 45212220; 45212290; 45212213 | Q15: Ver | R15: PCAP | S15: 46310 | T15: 46318.625 | U15: 2026-10-26: estado EV → ADJ
A16: En plazo | B16: 46346.999 | C16: 8318780.9 | D16: 8318780.9 | E16: Andalucía | F16: Sevilla | H16: Junta de Gobierno del Ayuntamiento de Carmona | I16: Obras para la ejecución del complejo de la música y el patrimonio en los antiguos mataderos de Carmona y la adecuación de sus entornos. | J16: EXP 25-173-22 | K16: Abierto | L16: 20 | M16: C*-5 | N16: 0.45 | P16: 45000000; 45212300; 45213230; 45112700; 45212321; 45454100 | Q16: Ver | R16: PCAP | S16: 46311 | T16: 46318.625
A17: En plazo | B17: 46337.999 | C17: 206393.65 | D17: 206393.65 | E17: Comunitat Valenciana | F17: Valencia | H17: Alcaldía del Ayuntamiento de Alberic | I17: El objeto del contrato es la ejecución de las obras destinadas a la Rehabilitación y adecuación de la antigua cisterna del Palacio Señorial de Alberic (usada como refugio antiaéreo en el transcurso de la Guerra Civil) como espacio de memoria democrática. | J17: 3019777K nueva licitación | K17: Abierto simplificado | L17: 4 | N17: 0 | P17: 45212350 | Q17: Ver | R17: PCAP | S17: 46321 | T17: 46318.621
A18: En plazo | B18: 46377.583 | C18: 21241200 | D18: 25355520 | E18: Comunitat Valenciana | F18: Valencia | H18: Presidencia de la Entidad Valenciana de Vivienda y Suelo | I18: Redacción del proyecto, ejecución de las obras y dirección facultativa para la construcción por procedimientos industrializados promovidas por la Entidad Valenciana de Vivienda y Suelo, en Silla y Carcaixent. | J18: CMAYOR/2026/EVHA0/0014 | K18: Abierto | L18: 12 | N18: 0.49 | O18: 4 | P18: 45211100; 71000000 | Q18: Ver | R18: PCAP | S18: 46314 | T18: 46318.613 | U18: 2026-10-20: plazo 2026-11-19 14:00 → 2026-12-21 14:00
A19: Adjudicada | B19: 46251.999 | C19: 396270 | D19: 396270 | E19: Comunitat Valenciana | F19: Valencia | G19: Vallada | H19: Alcaldía del Ayuntamiento de Vallada | I19: Reurbanización calles San Ramón, Santa Teresa y San lorenzo con realización de red separativa de pluviales, renovación de red de saneamiento y de agua potable, y sustitución de pavimentos | J19: 2685373K1 | K19: Abierto simplificado | L19: 5 | N19: 0 | P19: 45231300; 45232130; 45233252; 45232410 | Q19: Ver | R19: PCAP | S19: 46311 | T19: 46318.61 | U19: 2026-10-26: estado EV → ADJ
A20: Pendiente de adjudicación | B20: 46195.999 | C20: 3063829.2 | D20: 3063829.2 | E20: Andalucía | F20: Sevilla | H20: Presidencia de la Diputación Provincial de Sevilla | I20: Rehabilitación del salón de actos de los centros sociales de miraflores | J20: 2025/000942-PAA | K20: Abierto | L20: 12 | M20: C6-5 | N20: 0 | P20: 45000000 | Q20: Ver | R20: PCAP | S20: 46321 | T20: 46318.609
A21: Pendiente de adjudicación | B21: 46314.999 | C21: 83128.44 | D21: 83128.44 | E21: Andalucía | F21: Málaga | G21: Málaga | H21: Subdirección General de Administración Financiera y Patrimonio de la Administración General del Estado en el Territorio | I21: Ejecución de las obras de Sustitución de las luminarias a tecnología LED en la instalación de iluminación interior de la Oficina de Extranjería en Málaga situada en la Calle Mauricio Moro Pareto nº 13 (Código Postal 29006 de Málaga) | J21: 202686026070 | K21: Abierto simplificado | L21: 1 | N21: 0 | P21: 45316000 | Q21: Ver | R21: PCAP | S21: 46321 | T21: 46318.607
A22: En plazo | B22: 46339.999 | C22: 76859.5 | D22: 76859.5 | E22: Andalucía | F22: Málaga | G22: Alameda | H22: Alcaldía del Ayuntamiento de Alameda | I22: Constituye el objeto del presente pliego la contratación para la ejecución de las obras de Proyecto de instalación solar fotovoltaica para autoconsumo de 55 kW para sondeo en El Camorrillo, Alameda,Málaga | J22: 1866/2026 | K22: Abierto simplificado | L22: 4 | N22: 0 | P22: 45310000; 09332000; 09300000; 09331200 | Q22: Ver | R22: PCAP | S22: 46321 | T22: 46318.606
A23: En plazo | B23: 46342.999 | C23: 166994.64 | D23: 217093.03 | E23: Comunitat Valenciana | F23: Valencia | H23: Consorcio Hospital General Universitario de Valencia | I23: Contrato de obras, responsable con el medioambiente, para la reforma y mejora de la eficiencia energética del centro de atención de urgencias (CAU) 24 horas en el CS Torrent I. | J23: CMAYOR/2027/HGUV0/0141 | K23: Abierto simplificado | L23: 4 | N23: 0.25 | P23: 45215100 | Q23: Ver | R23: PCAP | S23: 46321 | T23: 46318.604
A24: Resuelta | B24: 46021.583 | C24: 172998.93 | D24: 172998.93 | E24: Andalucía | F24: Cádiz | G24: La Línea de La Concepción | H24: Alcaldía del Ayuntamiento de la Línea de la Concepción | I24: contrato de obra de “Proyecto de ejecución de pistas de deporte playa en Ciudad Deportiva de La Línea de la Concepción | J24: 118/25 | K24: Abierto simplificado | L24: 3 | N24: 0.25 | P24: 45212200; 45212000; 45210000; 45212210; 45000000; 45200000 | Q24: Ver | R24: PCAP | S24: 46321 | T24: 46318.604
A25: Pendiente de adjudicación | B25: 46232.562 | C25: 1812017.5 | D25: 1812017.5 | E25: Andalucía | F25: Cádiz | H25: Junta de Gobierno del Ayuntamiento de Chiclana de la Frontera | I25: Obras de transformación de carretera de Pago del Humo en vía urbana. | J25: 31/2026 | K25: Abierto simplificado | L25: 12 | M25: G6-4 | N25: 0.25 | P25: 45233140 | Q25: Ver | R25: PCAP | S25: 46311 | T25: 46318.602
A26: En plazo | B26: 46336.999 | C26: 132467.55 | D26: 132467.55 | E26: Comunitat Valenciana | F26: Valencia | H26: Servicio de Emergencias Sanitarias de la Comunitat Valenciana. Dirección Económica-Gerencia | I26: Dirección de obra y obra para la adecuación y habilitación de las instalaciones e infraestructuras sitas en la localidad de Sueca del Servicio de Emergencias Sanitarias de la Comunitat Valenciana. | J26: CNMY 1656/2026 | K26: Abierto simplificado | L26: 3.3 | N26: 0 | O26: 2 | P26: 45215100; 71240000; 71317210 | Q26: Ver | R26: PCAP | S26: 46310 | T26: 46318.601 | U26: 2026-10-22: plazo 2026-10-21 23:59 → 2026-11-10 23:59
A27: En plazo | B27: 46336.999 | C27: 358728.57 | D27: 358728.57 | E27: Andalucía | F27: Málaga | H27: Gerente de la Gerencia Municipal de Urbanismo del Ayuntamiento de Málaga | I27: Proyecto de remodelación de la plaza de la Biznaga en Cruz de Humilladero. Actuación cofinanciada por la Unión Europea a través del Fondo Europeo de Desarrollo Regional (FEDER), Programa Plurirregional de España (POPE) (2021-2027) | J27: 2026000065/GMU/OBR/ABR_SMPL | K27: Abierto simplificado | L27: 4 | N27: 0 | P27: 45233200; 45112710 | Q27: Ver | R27: PCAP | S27: 46317 | T27: 46318.601
A28: En plazo | B28: 46342.999 | C28: 3636363.6 | D28: 3636363.6 | E28: Andalucía | F28: Almería | H28: Junta de Gobierno de la Diputación Provincial de Almería | I28: Gran Eco-bulevard Vera - Palomares. Este Proyecto Podrá Ser Cofinanciado Por La Unión Europea A Través Del Fondo Europeo De Desarrollo Regional (feder) En El Marco Del Programa Plurirregional De Españ 9PAI-LEVANTE30 | J28: 2026/D31000/006-002/00004 | K28: Abierto | L28: 12.2 | M28: I1-4; G6-4 | N28: 0.25 | P28: 45111291 | Q28: Ver | R28: PCAP | S28: 46317 | T28: 46318.6
A29: Pendiente de adjudicación | B29: 46296.542 | C29: 450480.72 | D29: 450480.72 | E29: Comunitat Valenciana | F29: Alicante | G29: Monforte del Cid | H29: Junta de Gobierno del Ayuntamiento de Monforte del Cid | I29: La ejecución de las obras definidas en el Proyecto Básico y de Mejoras de Ejecución denominado Acondicionamiento de Café-Bar del Polideportivo Municipal y espacio libre anexo | J29: 3022/2026 Acondicionamiento cafe bar polideportivo | K29: Abierto simplificado | L29: 8 | N29: 0 | P29: 45000000; 45453100; 45210000; 45300000 | Q29: Ver | R29: PCAP | S29: 46310 | T29: 46318.599
A30: Adjudicada | B30: 46275.999 | C30: 173616.64 | D30: 173616.64 | E30: Andalucía | F30: Málaga | G30: ALAMEDA | H30: Alcaldía del Ayuntamiento de Alameda | I30: Obras de pavimentado de calle almendros, prolongación Avenida la Libertad y prolongación Blas Infante en el núcleo urbano de Alameda (Málaga), consistentes en la mejora del estado del firme y pavimentación sobre la calzada existente | J30: 1909/2026 | K30: Abierto simplificado | L30: 1 | N30: 0 | P30: 45233252 | Q30: Ver | R30: PCAP | S30: 46321 | T30: 46318.598
A31: Adjudicada | B31: 46215.999 | C31: 132231.4 | D31: 132231.4 | E31: Andalucía | F31: Málaga | G31: ALAMEDA | H31: Alcaldía del Ayuntamiento de Alameda | I31: Renovación del pavimento del pabellón de deportes José Francisco Torres Narbona, del Ayuntamiento de Alameda, a fin de mejorar el pavimento para la práctica deportiva, especialmente en lo concerniente a la práctica de futbol sala, baloncesto y balonmano, conforme a las especificaciones recogidas en el Pliego de Prescripciones Técnicas y el PCAP | J31: 1478/2026 | K31: Abierto simplificado | L31: 1 | N31: 0 | P31: 45212600 | Q31: Ver | R31: PCAP | S31: 46321 | T31: 46318.598
A32: Adjudicada | B32: 46300.625 | C32: 245175.69 | D32: 245175.69 | E32: Andalucía | F32: Cádiz | H32: Delegación Especial del Estado en el Consorcio de la Zona Franca de Cádiz | I32: Obras necesarias para la ejecución del proyecto de Reparacion de las zonas A-1, A-2, B-1, B-2, C-1, C-2 de la cubierta de la nave 1 del Recinto Interior de la Zona Franca de Cádiz. | J32: CO-0205-2026-00-A | K32: Abierto simplificado | L32: 3.5 | N32: 0.25 | P32: 45261420; 45261910 | Q32: Ver | R32: PCAP | S32: 46310 | T32: 46318.596 | U32: 2026-10-26: estado EV → ADJ
A33: En plazo | B33: 46323.999 | C33: 82639.55 | D33: 82639.55 | E33: Andalucía | F33: Jaén | G33: TORREPEROGIL | H33: Alcaldía del Ayuntamiento de Torreperogil | I33: Recuperación de Muralla histórica y de la cerca del Antiguo Cementerio en calle Perogil, en el municipio de Torreperogil. | J33: 2266/2026 | K33: Abierto simplificado | L33: 5 | N33: 0.2 | P33: 45454100 | Q33: Ver | R33: PCAP | S33: 46310 | T33: 46318.594
A34: Pendiente de adjudicación | B34: 46279.542 | C34: 935351.01 | D34: 1028886.1 | E34: Comunitat Valenciana | F34: Valencia | H34: Presidencia de la Diputación Provincial de Valencia | I34: Ac-631/O. Obras de continuidad y accesibilidad del itinerario ciclo peatonal en la carretera CV-649 entre Vallada y la estación de ferrocarril (TM de Vallada) | J34: 1696/26/CAR | K34: Abierto | L34: 8 | M34: G4-4 | N34: 0.34 | P34: 45233120; 45233162 | Q34: Ver | R34: PCAP | S34: 46317 | T34: 46318.593
A35: Resuelta | B35: 44568.999 | C35: 137452.34 | D35: 137452.34 | E35: Comunitat Valenciana | F35: Valencia | H35: Concejalía Delegada de Contratación del Ajuntament de València | I35: Contrato de obras para la ejecución del proyecto denominado “Rebaje de aceras en pasos de peatones, acondicionamientos de baldosas y paso de peatones sobreelevado en Benimàmet (València)”.- | J35: 04101/2021/257-O | K35: Abierto simplificado | L35: 3 | N35: 0 | P35: 45233251 | Q35: Ver | R35: PCAP | S35: 46321 | T35: 46318.592
A36: Pendiente de adjudicación | B36: 46316.999 | C36: 330257.67 | D36: 330257.67 | E36: Andalucía | F36: Málaga | G36: Cuevas del Becerro | H36: Alcaldía del Ayuntamiento de Cuevas del Becerro | I36: Remodelación completa de la tubería de abastecimiento general que parte desde las inmediaciones del depósito regulador y discurre por la continuación del paseo del Castillejo y la avenida La Fuentezuela, la remodelación completa de dicha avenida y la instalación de un grupo de presión para resolver el proble-ma de baja presión en la zona. | J36: 200/2026 | K36: Abierto simplificado | L36: 6 | N36: 0.1 | P36: 45230000; 45231100; 45233260; 45233140 | Q36: Ver | R36: PCAP | S36: 46321 | T36: 46318.59
A37: En plazo | B37: 46338.999 | C37: 67298.88 | D37: 67298.88 | E37: Andalucía | F37: Almería | H37: Junta de Gobierno de la Diputación Provincial de Almería | I37: Instalación De Sistema De Abastecimiento De Agua Contra Incendios En Residencia Asistida De Mayores. Fase 1, Unidad 14 Y Unidad 10-12. 6PGM2026 | J37: 2026/D31000/006-013/00066 | K37: Abierto simplificado | L37: 3 | N37: 0.25 | P37: 45343200 | Q37: Ver | R37: PCAP | S37: 46321 | T37: 46318.59
A38: Adjudicada | B38: 46232.999 | C38: 666460.78 | D38: 666460.78 | E38: Comunitat Valenciana | F38: Alicante | H38: Junta de Gobierno del Ayuntamiento de Elche | I38: Obras de adaptación viaria en puntos conflictivos de tráfico en el término municipal de Elche. | J38: OBR/ABR_SMPL/2026000107 | K38: Abierto simplificado | L38: 6 | M38: G4-3 | N38: 0.2 | P38: 45233120 | Q38: Ver | R38: PCAP | S38: 46311 | T38: 46318.589 | U38: 2026-10-26: estado EV → ADJ
A39: Pendiente de adjudicación | B39: 46283.833 | C39: 533572.55 | D39: 533572.55 | E39: Andalucía | F39: Granada | G39: Atarfe (Granada) | H39: Dirección Gerente de Aguas Vega Sierra Elvira, S.A. | I39: Renovación de redes de calle jaén y calle marbella Maracena (Granada) | J39: Obras 13/2026 | K39: Abierto | L39: 6 | N39: 0.4 | P39: 45200000; 45231100; 45232100; 45220000; 44160000 | Q39: Ver | R39: PCAP | S39: 46315 | T39: 46318.588
A40: En plazo | B40: 46338.999 | C40: 983261.73 | D40: 983261.73 | E40: Comunitat Valenciana | F40: Alicante | H40: Junta de Gobierno del Ayuntamiento de Aspe | I40: Contrato Administrativo Obras rehabilitación de edificio de viviendas de calle Azorin y urbanizacion anexa en Aspe , Alicante conforme proyecto redactado por UTE PLAN A3 ARQUITECTURA E INGENIERIA, AKTUA MANAGEMENT Y CARMEN TORRES PEREZ | J40: 2026/46-GUACON | K40: Abierto simplificado | L40: 10 | N40: 0 | P40: 45000000 | Q40: Ver | R40: PCAP | S40: 46321 | T40: 46318.587
A41: Resuelta | B41: 46122.999 | C41: 181503.27 | D41: 181503.27 | E41: Comunitat Valenciana | F41: Valencia | H41: Junta de Gobierno del Ayuntamiento de Sagunto | I41: Contrato de obras para la sustitución y adecuación de elementos de protección en la pasarela peatonal sobre la línea F.F.C.C. Valencia-Sagunto-Barcelona, situación en la calle de la Estación de Sagunto | J41: 13/26-C | K41: Restringido | L41: 45 | N41: 0 | O41: 1 | P41: 45000000 | Q41: Ver | R41: PCAP | S41: 46321 | T41: 46318.584
A42: Resuelta | B42: 46280.999 | C42: 123966.94 | D42: 123966.94 | E42: Andalucía | F42: Cádiz | G42: SAN JOSE DEL VALLE | H42: Alcaldía del Ayuntamiento de San José del Valle | I42: 2ª Fase de Adaptación de Centro Cultural. Plan de Cooperación a las Obras y Servicios de Competencia Municipal PPCOS 2026-2027 | J42: 2244-2026 | K42: Abierto simplificado | L42: 6 | N42: 0 | P42: 45000000; 45200000 | Q42: Ver | R42: PCAP | S42: 46321 | T42: 46318.583
A43: En plazo | B43: 46331.999 | C43: 5236971.6 | D43: 5236971.6 | E43: Andalucía | F43: Huelva | G43: HUELVA | H43: Junta de Gobierno de la Diputación Provincial de Huelva | I43: El presente contrato tiene por objeto la rehabilitación del firme de diversas carreteras provinciales pertenecientes al Plan de inversiones del Servicio de Carreteras y Caminos 2025 y Tu Diputación Actua. | J43: 2026/CMY_03/000148 | K43: Abierto | L43: 3 | N43: 0 | O43: 6 | P43: 45233000 | Q43: Ver | R43: PCAP | S43: 46321 | T43: 46318.582
A44: Resuelta | B44: 46238.999 | C44: 57851.23 | D44: 57851.23 | E44: Comunitat Valenciana | F44: Valencia | G44: Utiel | H44: Alcaldía del Ayuntamiento de Utiel | I44: Reurbanización de calles en la Aldea de las Casas de Utiel, incluida dentro del Plan Abierto del Plan de Inversiones de Diputación de Valencia para los años 2024-2027 | J44: 8151/2025 | K44: Abierto simplificado | L44: 1 | N44: 0 | P44: 45200000 | Q44: Ver | R44: PCAP | S44: 46321 | T44: 46318.578
A45: Pendiente de adjudicación | B45: 46309.999 | C45: 112245.5 | D45: 112245.5 | E45: Andalucía | F45: Málaga | G45: Colmenar, Málaga | H45: Alcaldía del Ayuntamiento de Colmenar | I45: Realización de las obras correspondientes al proyecto denominado 'Mejora red de abastecimiento de agua en Jaldarín, Las Pitas y Carrasco' | J45: 1024/2026 | K45: Abierto simplificado | L45: 3 | N45: 0 | P45: 45112000; 45232151; 90513000; 45232150; 45111200 | Q45: Ver | R45: PCAP | S45: 46321 | T45: 46318.577
A46: Resuelta | C46: 591987.5 | D46: 716304.88 | E46: Andalucía | F46: Granada | H46: Demarcación de Carreteras del Estado en Andalucía Oriental | I46: Sustitución de pretil y pantalla antivandálica en la estructura de la A-7 sobre el ferrocarril, en el P.K. 779+550. T.M. Huércal de Almería, provincia de Almería. LOTE 1 | J46: EM33-AL-260004.L1 | K46: Negociado sin publicidad | L46: 5 | P46: 45000000 | Q46: Ver | S46: 46321 | T46: 46318.576
A47: Pendiente de adjudicación | B47: 46308.583 | C47: 300493.09 | D47: 300493.09 | E47: Andalucía | F47: Córdoba | G47: Montalbán | H47: Presidenta de Mancomunidad de Municipios Campiña Sur Cordobesa | I47: Contrato de obras para la ejecución de la actuación, mejora y adecuación de las infraestructuras deportivas municipales de Montalbán de Córdoba (Córdoba), incluida en el plan de actuación integrado (PAI) Conecta Campiña Sur, desarrollado en el marco de la estrategia de desarrollo integrado local (EDIL) y cofinanciado por la Unión Europea. | J47: GEX1188/2026 | K47: Abierto simplificado | L47: 2.5 | N47: 0 | P47: 45212200 | Q47: Ver | R47: PCAP | S47: 46321 | T47: 46318.574
A48: Pendiente de adjudicación | B48: 46286.999 | C48: 596379.84 | D48: 715655.81 | E48: Andalucía | F48: Sevilla | G48: Sevilla | H48: Comisión Ejecutiva de Mercados Centrales de Abastecimiento de Sevilla S.A. (MERCASEVILLA S.A.) | I48: Contrato de obras de restauración y pintura del exterior del Edificio Administrativo, renovación de la rotulación corporativa, y rotulación exterior de varios espacios de Mercados Centrales de Abastecimiento de Sevilla, S.A. (Mercasevilla, S.A.). Expte. 2026/190. | J48: 2026/190 | K48: Abierto | L48: 4 | M48: C4-3 | N48: 0.3 | P48: 45000000 | Q48: Ver | R48: PCAP | S48: 46321 | T48: 46318.57
A49: Pendiente de adjudicación | B49: 46316.999 | C49: 37662.81 | D49: 45195.37 | E49: Andalucía | F49: Málaga | H49: Gerencia de la Empresa Malagueña de Transportes S.A.M. | I49: El contrato tiene por objeto la sustitución y reforma integral del sistema de producción de Agua Caliente Sanitaria (ACS) de los vestuarios del taller de EMTSAM situados en Camino San Rafael nº 97 de Málaga, con el alcance funcional y técnico definido en el PPTP y sus anexos. | J49: 022/2026 | K49: Abierto | L49: 3 | N49: 0 | P49: 45330000; 45331000 | Q49: Ver | R49: PCAP | S49: 46321 | T49: 46318.57
A50: Pendiente de adjudicación | B50: 46308.999 | C50: 269136.45 | D50: 269136.45 | E50: Comunitat Valenciana | F50: Alicante | H50: Junta de Gobierno del Ayuntamiento de Elche | I50: Obras de mantenimiento de espacios públicos peatonales en los distritos urbanos y rurales 2026 (aceras distritos) | J50: OBR/ABR_SMPL/2026000147 | K50: Abierto simplificado | L50: 12 | N50: 0.25 | P50: 45233140 | Q50: Ver | R50: PCAP | S50: 46310 | T50: 46318.57
A51: En plazo | B51: 46336.999 | C51: 223140.02 | D51: 245454.02 | E51: Comunitat Valenciana | F51: Valencia | H51: Concejalía Delegada de Contratación del Ajuntament de València | I51: Obras correspondientes al proyecto básico y ejecución Ruta Salut al Grau 2026. Actuación seleccionada en la consulta ciudadana sobre inversiones en barrios de los presupuestos participativos DECIDIM VLC (VLC 2020-4987, VLC 2022-6041).- | J51: 04101/2026/215-O | K51: Abierto simplificado | L51: 5 | N51: 0 | P51: 45212200 | Q51: Ver | R51: PCAP | S51: 46317 | T51: 46318.569
A52: Resuelta | C52: 2838149.1 | D52: 3434160.4 | E52: Andalucía | F52: Granada | H52: Demarcación de Carreteras del Estado en Andalucía Oriental | I52: Reparación de firme en la autovía A-7 entre los PP.KK. 922+520 límite con la provincia de Granada y 983+700 límite con el sector MA-01, provincia de Málaga. LOTE 5 | J52: EM32-MA-260001.L5 | K52: Negociado sin publicidad | L52: 5 | P52: 45000000 | Q52: Ver | S52: 46321 | T52: 46318.566
A53: En plazo | B53: 46338.999 | C53: 132325.5 | D53: 132325.5 | E53: Comunitat Valenciana | F53: Alicante | H53: Alcaldía del Ayuntamiento del Poble Nou de Benitatxell | I53: obra de consolidación del perímetro de la excavación arqueológica del lavadero dels Pous de Abiar | J53: 4472/2026 | K53: Abierto simplificado | L53: 2 | N53: 0.25 | P53: 45212350; 45112500; 45223500 | Q53: Ver | R53: PCAP | S53: 46321 | T53: 46318.565
A54: En plazo | B54: 46335.999 | C54: 181000.01 | D54: 181000.01 | E54: Andalucía | F54: Jaén | H54: Fundación para la Investigación Biosanitaria de Andalucía Oriental - Alejandro Otero (FIBAO) | I54: Obra para la adaptación funcional del área de oncología del Hospital Médico - Quirúrgico de Jaén. | J54: 027_2026 | K54: Abierto simplificado | L54: 3 | N54: 0 | P54: 45453100 | Q54: Ver | R54: PCAP | S54: 46321 | T54: 46318.565
A55: Resuelta | C55: 3382028.2 | D55: 4092254.2 | E55: Andalucía | F55: Granada | H55: Demarcación de Carreteras del Estado en Andalucía Oriental | I55: Reparación de firme en la autovía A-45 entre los PP.KK 120+000 Y 142+400, provincia de Málaga. LOTE 4 | J55: EM32-MA-260001.L4 | K55: Negociado sin publicidad | L55: 5 | P55: 45000000 | Q55: Ver | S55: 46321 | T55: 46318.565
A56: En plazo | B56: 46329.999 | C56: 3060580.6 | D56: 3060580.6 | E56: Andalucía | F56: Huelva | H56: Pleno del Ayuntamiento de Punta umbría | I56: Ejecución de las obras para la renovación y mejora de la eficiencia energética de las instalaciones de alumbrado público exterior en el Municipio de Punta Umbría (Huelva) | J56: 5163/2026 | K56: Abierto | L56: 9 | M56: I1-4 | N56: 0.25 | P56: 45316100; 45315600; 34928500 | Q56: Ver | R56: PCAP | S56: 46310 | T56: 46318.564
A57: Pendiente de adjudicación | B57: 46300.999 | C57: 52913.35 | D57: 52913.35 | E57: Comunitat Valenciana | F57: Alicante | H57: Junta de Gobierno del Ayuntamiento de Elche | I57: Obras para los trabajos de identificación y documentación de vestigios arqueológicos en el solar sito entre la Avenida de Candalix y la Calle Nuestra Señora de la Cabeza. | J57: OBR/ABR_SMPL/2026000139 | K57: Abierto simplificado | L57: 1.2 | N57: 0 | P57: 45112450; 71351811; 71351914; 45122000 | Q57: Ver | R57: PCAP | S57: 46310 | T57: 46318.563
A58: Adjudicada | B58: 46265.417 | C58: 126817.17 | D58: 126817.17 | E58: Andalucía | F58: Málaga | H58: Empresa de Transformación Agraria S.A.,S.M.E., M.P., (TRAGSA) | I58: Suministro y ejecución de instalación de calefacción mediante canalización vista de acero inoxidable e instalación de radiadores en varios edificios públicos de los municipios de Gaucín y Júcar (Málaga) | J58: TSA0083485 | K58: Abierto simplificado | L58: 4 | M58: J2-1 | N58: 0 | O58: 2 | P58: 45331000 | Q58: Ver | R58: PCAP | S58: 46321 | T58: 46318.56
A59: Pendiente de adjudicación | B59: 46317.999 | C59: 200711.23 | D59: 200711.23 | E59: Comunitat Valenciana | F59: Valencia | G59: Alborache | H59: Pleno del Ayuntamiento de Alborache | I59: Renovación en la Casa de los Maestros de Alborache | J59: 498/2026 | K59: Abierto simplificado | L59: 6 | N59: 0.25 | P59: 45000000; 45212170; 45111100 | Q59: Ver | R59: PCAP | S59: 46321 | T59: 46318.56
A60: Resuelta | B60: 46259.999 | C60: 647199.04 | D60: 647199.04 | E60: Andalucía | F60: Córdoba | H60: Junta de Gobierno del Ayuntamiento de Palma del Río | I60: Obras contenidas en el Proyecto de Reasfaltado de varias Avenidas y Calles del municipio de Palma del Río (Córdoba) | J60: OB-01/2026 | K60: Abierto simplificado | L60: 2 | M60: G4-3 | N60: 0 | P60: 45233223; 45233252; 45233222 | Q60: Ver | R60: PCAP | S60: 46321 | T60: 46318.559
A61: En plazo | B61: 46338.999 | C61: 162925.04 | D61: 162925.04 | E61: Andalucía | F61: Sevilla | H61: Alcaldía del Ayuntamiento de Mairena del Aljarafe | I61: Obras para la legalización de la actividad de los Centros de la 3ª Edad "Los Veteranos", "Sal si puedes", y "La Edad de Oro" del municipio de Mairena del Aljarafe, en tres lotes.- | J61: 15600/2026 | K61: Abierto simplificado | L61: 2 | N61: 0 | O61: 3 | P61: 45000000 | Q61: Ver | R61: PCAP | S61: 46321 | T61: 46318.558
A62: Pendiente de adjudicación | B62: 46316.999 | C62: 261514.4 | D62: 261514.4 | E62: Comunitat Valenciana | F62: Valencia | G62: ALBORACHE | H62: Pleno del Ayuntamiento de Alborache | I62: Ejecución de las obras de realización de una plataforma única en la Calle de Abajo de Alborache, dentro del Plan abierto de Inversiones 2024-2027 de la Diputación de Valencia. | J62: 74/2026 | K62: Abierto simplificado | L62: 3 | N62: 0 | P62: 45000000; 45233252; 45332000; 45233140 | Q62: Ver | R62: PCAP | S62: 46321 | T62: 46318.558
A63: En plazo | B63: 46338.999 | C63: 67768.59 | D63: 67768.59 | E63: Andalucía | F63: Cádiz | G63: Benalup-Casas Viejas | H63: Junta de Gobierno Local del Ayuntamiento de Benalup-Casas Viejas | I63: Sustitución de carpintería exterior y pintura del CEIP Tajo de las Figuras. | J63: 1237/2026 | K63: Abierto simplificado | L63: 2 | N63: 0 | P63: 45421130; 45442100 | Q63: Ver | R63: PCAP | S63: 46321 | T63: 46318.557
A64: En plazo | B64: 46339.417 | C64: 538193.71 | D64: 538193.71 | E64: Andalucía | F64: Cádiz | G64: Cádiz | H64: Junta de Gobierno del Ayuntamiento de Cádiz | I64: Urbanización calle Juan de la Cierva, Dársena y Fernández Cossío, a implementar en el PAI de Cádiz, Europa transforma nuestros barrios, cofinanciado por la unión europea a través del fondo europeo de desarrollo regional FEDER en el marco del programa plurirregional de España 2021-2027 | J64: 2026/143 | K64: Abierto simplificado | L64: 5 | M64: G6-3 | N64: 0 | P64: 45233140; 45232400 | Q64: Ver | R64: PCAP | S64: 46321 | T64: 46318.557
A65: Pendiente de adjudicación | B65: 46296.999 | C65: 8348036.8 | D65: 8348036.8 | E65: Comunitat Valenciana | F65: Alicante | H65: Junta de Gobierno del Ayuntamiento de Elche | I65: Contrato de obras de Rehabilitación del Convento de la Merced | J65: OBR/ABR/2026000130 | K65: Abierto | L65: 36 | M65: C7-5; C4-5; C8-5; K7-4 | N65: 0.4 | P65: 45000000; 45200000 | Q65: Ver | R65: PCAP | S65: 46310 | T65: 46318.557
A66: En plazo | B66: 46338.75 | C66: 358510.65 | D66: 394361.72 | E66: Comunitat Valenciana | F66: Alicante | G66: Alicante (Alacant) | H66: Junta de Gobierno del Ayuntamiento de Santa Pola | I66: Licitación para la contratación de las obras de mejora de aceras de varias calles del Municipio de Santa Pola | J66: 13981/2026 | K66: Abierto simplificado | L66: 4 | N66: 0.45 | P66: 45111000; 45233200; 77310000; 45233252 | Q66: Ver | R66: PCAP | S66: 46321 | T66: 46318.556
A67: Resuelta | B67: 46254.999 | C67: 49719.85 | D67: 49719.85 | E67: Comunitat Valenciana | F67: Alicante | G67: Agost | H67: Alcaldía del Ayuntamiento de Agost | I67: Reforma parcial en edificio del Centro Social para adecuación de despachos | J67: 2039/2026 | K67: Abierto simplificado | L67: 1.6 | N67: 0 | O67: 2 | P67: 45450000; 39515410 | Q67: Ver | R67: PCAP | S67: 46321 | T67: 46318.555
A68: Pendiente de adjudicación | B68: 46316.583 | C68: 290135.38 | D68: 290135.38 | E68: Comunitat Valenciana | F68: Alicante | G68: San Vicente del Raspeig | H68: Presidencia Delegada del Consorcio Provincial para el Servicio de Prevención y Extinción de Incendios y Salvamento de Alicante | I68: Obra de reparación e impermeabilización del Hangar en el Parque de bomberos de San Vicente | J68: PA S O-1/2026 | K68: Abierto simplificado | L68: 3 | N68: 0 | P68: 45261000 | Q68: Ver | R68: PCAP | S68: 46321 | T68: 46318.555
A69: En plazo | B69: 46338.999 | C69: 859232.28 | D69: 859232.28 | E69: Andalucía | F69: Sevilla | H69: Vicepresidencia del Instituto Municipal de Deportes del Ayuntamiento de Sevilla | I69: Obras de reparación, renovación y adecuación superficial de los pavimentos de las pistas deportivas exteriores adscritas a los Centros Deportivos (CD) del Instituto Municipal de Deportes (IMD) del Ayuntamiento de Sevilla. | J69: 2026/000905 | K69: Abierto simplificado | L69: 6 | N69: 0 | P69: 45432100; 45212290; 45236119; 45212213 | Q69: Ver | R69: PCAP | S69: 46321 | T69: 46318.553
A70: En plazo | B70: 46335.999 | C70: 4566296.3 | D70: 4566296.3 | E70: Andalucía | F70: Granada | G70: OGIJARES | H70: Presidencia de la Diputación Provincial de Granada | I70: Refundido final urbanización del Plan Especial "La Aurora" en Ogíjares. | J70: OB-037/26 | K70: Abierto | L70: 18 | M70: G6-5; E7-5; I9-4 | N70: 0 | P70: 45220000; 45233252; 45232200; 45316110; 45232150; 45232410; 45233140 | Q70: Ver | R70: PCAP | S70: 46310 | T70: 46318.549
A71: En plazo | B71: 46335.999 | C71: 67916.16 | D71: 67916.16 | E71: Andalucía | F71: Córdoba | H71: Empresa de Transformación Agraria S.A.,S.M.E., M.P., (TRAGSA) | I71: Obra asfaltado de viales para el proyecto de ejecución "Urbanización Manzana 2 y Manzana 16 (parcial) de la Unidad de ejecución UE-1 SUS19 "Autovía Norte" en la Carlota, Córdoba" | J71: TSA0084208 | K71: Abierto simplificado | L71: 12 | N71: 0 | P71: 45233222 | Q71: Ver | R71: PCAP | S71: 46321 | T71: 46318.549
A72: Adjudicada | B72: 46297.999 | C72: 62030.11 | D72: 62030.11 | E72: Andalucía | F72: Málaga | H72: Concejalía Delegada de la Presidencia de la Junta Municipal del Distrito nº 10, Puerto de la Torre del Ayuntamiento de Málaga | I72: Nuevo aparcamiento en Avenida Escritora Matilde del Nido. Fase II. | J72: PASA 26/07/456 | K72: Abierto simplificado | L72: 2 | N72: 0 | P72: 45000000 | Q72: Ver | R72: PCAP | S72: 46321 | T72: 46318.546
A73: En plazo | B73: 46338.999 | C73: 223895.1 | D73: 223895.1 | E73: Andalucía | F73: Jaén | G73: JAEN | H73: Presidencia de la Diputación Provincial de Jaén | I73: Contrato de obras de renovación instalación eléctrica y obras en edificios del área de Recaudación de Jaén. | J73: CO-2026/001163 | K73: Abierto simplificado | L73: 5 | N73: 0.25 | P73: 45453100 | Q73: Ver | R73: PCAP | S73: 46321 | T73: 46318.546
A74: Adjudicada | B74: 46293.999 | C74: 131757.03 | D74: 131757.03 | E74: Andalucía | F74: Córdoba | G74: Baena | H74: Alcaldía del Ayuntamiento de Baena | I74: Obras de Reurbanización de la Calle Doctora Antonia Martinez Casado | J74: OBRAS-01/2026 | K74: Abierto simplificado | L74: 5 | N74: 0 | P74: 45233252; 45233200; 45233140; 45232410; 45231100 | Q74: Ver | R74: PCAP | S74: 46321 | T74: 46318.545
A75: Adjudicada | B75: 46280.999 | C75: 1652803.6 | D75: 1652803.6 | E75: Comunitat Valenciana | F75: Castellón | G75: Burriana (Castellón) | H75: Alcaldía del Ayuntamiento de Borriana | I75: Obras de construcción de un nuevo Centro Sanitario de Atención Primaria en el Puerto de Burriana (Castellón) financiado por la Generalitat Valenciana en el marco del Decreto-Ley 12/2025, de 22 de julio, del Consell. | J75: BURR 7969/2026-PM 10/25 | K75: Abierto simplificado | L75: 12 | M75: C*-4 | N75: 0.2 | P75: 45215100 | Q75: Ver | R75: PCAP | S75: 46321 | T75: 46318.544
A76: Pendiente de adjudicación | B76: 46301.999 | C76: 82644.62 | D76: 82644.62 | E76: Andalucía | F76: Córdoba | G76: Fuente Obejuna | H76: Alcaldia del Ayuntamiento de Fuente Obejuna | I76: Contrato de obras del Proyecto de muro de contención en Calle Orden de Calatrava 2ª fase | J76: 6438/2026 | K76: Abierto simplificado | L76: 6 | N76: 0 | P76: 45000000; 45262520; 45210000 | Q76: Ver | R76: PCAP | S76: 46321 | T76: 46318.544
A77: En plazo | B77: 46339.542 | C77: 900915.88 | D77: 900915.88 | E77: Comunitat Valenciana | F77: Castellón | G77: L'Alcora | H77: Alcaldía del Ayuntamiento de L'Alcora | I77: Ejecución del proyecto de obras de "Derribo y adecuación de solar de la antgua fábrica de Azulejos Sanchis de l'Alcora". | J77: 9083/2026 | K77: Abierto simplificado | L77: 4 | M77: C1-4 | N77: 0.25 | P77: 45110000 | Q77: Ver | R77: PCAP | S77: 46321 | T77: 46318.543
A78: Pendiente de adjudicación | B78: 46300.999 | C78: 216584.41 | D78: 259901.28 | E78: Comunitat Valenciana | F78: Alicante | H78: Junta de Gobierno del Ayuntamiento de Elche | I78: Ejecución de trabajos de mejora, regeneración y modernización del Polígono Industrial de Carrús. Actuaciones de regeneración paisajística (subvencionado por IVACE) | J78: OBR/ABR_SMPL/2026000138 | K78: Abierto simplificado | L78: 2 | N78: 0 | P78: 45112700; 45233140; 45232121 | Q78: Ver | R78: PCAP | S78: 46310 | T78: 46318.54
A79: Pendiente de adjudicación | B79: 46296.75 | C79: 299958.91 | D79: 299958.91 | E79: Comunitat Valenciana | F79: Valencia | G79: Algemesí | H79: Junta de Gobierno del Ayuntamiento de Algemesí | I79: Ejecución de las obras de derribo del Velódromo Municipal de Algemesí | J79: 6059/2026 | K79: Abierto simplificado | L79: 2 | N79: 0 | P79: 45111000 | Q79: Ver | R79: PCAP | S79: 46310 | T79: 46318.537
A80: Resuelta | B80: 46290.999 | C80: 53723.03 | D80: 53723.03 | E80: Comunitat Valenciana | F80: Castellón | G80: Costur | H80: Pleno del Ayuntamiento de Costur | I80: Ejecución de las obras del proyecto de Mejoras de la accesibilidad en el Ayuntamiento de Costur | J80: 358/2026 | K80: Negociado sin publicidad | L80: 2 | N80: 0.25 | P80: 45000000; 45262700; 45313100 | Q80: Ver | R80: PCAP | S80: 46321 | T80: 46318.537
A81: Pendiente de adjudicación | B81: 46289.999 | C81: 398450.06 | D81: 398450.06 | E81: Andalucía | F81: Sevilla | G81: SAN JUAN DE AZNALFARACHE | H81: Junta de Gobierno del Ayuntamiento San Juan de Aznalfarache | I81: ejecución de las obras contempladas en el “Proyecto de Ejecución de Glorieta de organización de tráfico sobre plataforma de cubrición de la Autovía A-8058” | J81: 5434/2026 | K81: Abierto simplificado | L81: 6 | N81: 0 | P81: 45000000 | Q81: Ver | R81: PCAP | S81: 46310 | T81: 46318.537
A82: Resuelta | B82: 46196.625 | C82: 281561.17 | D82: 281561.17 | E82: Comunitat Valenciana | F82: Castellón | G82: Vinaròs | H82: Dirección Territorial de Educación y Universidades de Castellón | I82: Sustitución parcial del vallado en el CEIP Nuestra Señora de la Asunción de Vinaros | J82: CMAYOR/2026/19Y14/0059 | K82: Abierto simplificado | L82: 4 | N82: 0 | P82: 45214210 | Q82: Ver | R82: PCAP | S82: 46321 | T82: 46318.533
A83: Adjudicada | B83: 46294.999 | C83: 154169 | D83: 154169 | E83: Comunitat Valenciana | F83: Castellón | G83: Navajas | H83: Alcaldía del Ayuntamiento de Navajas | I83: Obras de adecuación y mejora del Polideportivo Municipal de Navajas. | J83: 386/2026 | K83: Abierto simplificado | L83: 6 | N83: 0.25 | P83: 45212200; 45212290 | Q83: Ver | R83: PCAP | S83: 46321 | T83: 46318.532
A84: En plazo | B84: 46342.999 | C84: 490067.3 | D84: 490067.3 | E84: Andalucía | F84: Huelva | G84: Chucena | H84: Alcaldía del Ayuntamiento de Chucena | I84: Ejecución de las obras contempladas en el Proyecto de Urbanización de la calle transversal a calle Cartuja. Fase 1, en el término municipal de Chucena (Huelva). | J84: 361/2026 | K84: Abierto simplificado | L84: 6 | N84: 0 | P84: 45230000 | Q84: Ver | R84: PCAP | S84: 46321 | T84: 46318.531
A85: Pendiente de adjudicación | B85: 46314.999 | C85: 7583129 | D85: 8341441.9 | E85: Comunitat Valenciana | F85: Valencia | H85: Junta de Gobierno del Ajuntament de València | I85: Obras de construcción del edificio de la Segunda Unidad de Distrito de la Policía Local.- | J85: 04101/2026/154-O | K85: Abierto | L85: 18 | M85: C*-6 | N85: 0 | P85: 45000000 | Q85: Ver | R85: PCAP | S85: 46318 | T85: 46318.53
A86: En plazo | B86: 46349.999 | C86: 59505.36 | D86: 59505.36 | E86: Andalucía | F86: Cádiz | H86: Gerencia de la Empresa Municipal de la Vivienda de Jerez, S.A. | I86: Contrato de obras de reparación y conservación de las pasarelas exteriores de acceso a los edificios de viviendas sitos en calle Tío Juanes n.º 2 y n.º 4 de Jerez de la Frontera. | J86: EMUVIJESA/PAS/10/2026 | K86: Abierto simplificado | L86: 2.5 | N86: 0 | P86: 45453100 | Q86: Ver | R86: PCAP | S86: 46321 | T86: 46318.53
A87: Resuelta | B87: 46309.999 | C87: 670701.35 | D87: 670701.35 | E87: Andalucía | F87: Málaga | H87: Junta de Gobierno del Ayuntamiento de Vélez-Málaga | I87: Reurbanización de la Calle Doctor Fleming de Torre del Mar. Tramo Calle Eduardo Iglesias Pérez - Calle Doctor Laureano Casquero. | J87: AVM.OBR-2026000015 | K87: Abierto simplificado | L87: 8 | M87: G6-2 | N87: 0 | P87: 45233252 | Q87: Ver | R87: PCAP | S87: 46321 | T87: 46318.528
A88: Pendiente de adjudicación | B88: 46311.542 | C88: 424023.1 | D88: 424023.1 | E88: Andalucía | F88: Málaga | H88: Junta de Gobierno del Ayuntamiento de Málaga | I88: Obras de subsanación de deficiencias de once centros de enseñanza infantil y primaria de la Ciudad de Málaga | J88: 116/26 | K88: Abierto simplificado | L88: 3 | N88: 0 | P88: 45000000; 45259000 | Q88: Ver | R88: PCAP | S88: 46321 | T88: 46318.527
A89: Pendiente de adjudicación | B89: 46314.999 | C89: 1782917.8 | D89: 1782917.8 | E89: Comunitat Valenciana | F89: Valencia | G89: Ontinyent | H89: Alcaldia del Ayuntamiento de Ontinyent | I89: Contratación de las obras de "Ampliación del cementerio municipal de Ontinyent" | J89: 2955403C | K89: Abierto simplificado | L89: 15 | M89: C2-4 | N89: 0.25 | P89: 45112714; 45236300; 45215400; 45233200; 45223800 | Q89: Ver | R89: PCAP | S89: 46321 | T89: 46318.523
A90: Pendiente de adjudicación | B90: 46314.999 | C90: 66307.65 | D90: 79569.18 | E90: Comunitat Valenciana | F90: Alicante | G90: Dolores | H90: Alcaldía del Ayuntamiento de Dolores | I90: Adecuación de la Avenida Príncipe de Asturias | J90: 3492/2026 | K90: Abierto simplificado | L90: 3 | N90: 0 | P90: 45233140; 45233220; 45316100; 77310000; 45231000 | Q90: Ver | R90: PCAP | S90: 46321 | T90: 46318.522
A91: En plazo | B91: 46322.458 | C91: 50129.2 | D91: 50129.2 | E91: Andalucía | F91: Granada | H91: Alcaldía del Ayuntamiento de Almuñécar | I91: Contrato de Obras de Mejora de protecciones y drenajes de varios caminos en el entorno del Río Jate, en el término municipal de Almuñécar, subvencionada por la Diputación Provincial de Granada `Subvención para inversiones de reparación de daños producidos por temporal e inversiones de carácter preventivo. - Línea 1. ´ | J91: 106/2026 (GEST 8481 BIS/2026) | K91: Negociado sin publicidad | L91: 3 | N91: 0 | P91: 45233200 | Q91: Ver | R91: PCAP | S91: 46314 | T91: 46318.522
A92: En plazo | B92: 46322.458 | C92: 61420.45 | D92: 61420.45 | E92: Andalucía | F92: Granada | H92: Alcaldía del Ayuntamiento de Almuñécar | I92: Obras para mejoras de protecciones y drenajes de varios caminos en el entorno del Río Verde, en el término municipal de Almuñécar. Subvencionado por la Diputación Provincial de Granada. | J92: 104/2026 (GEST 8478 BIS/2026) | K92: Negociado sin publicidad | L92: 3 | N92: 0 | P92: 45233200 | Q92: Ver | R92: PCAP | S92: 46314 | T92: 46318.521
A93: En plazo | B93: 46322.458 | C93: 65480.44 | D93: 65480.44 | E93: Andalucía | F93: Granada | H93: Alcaldía del Ayuntamiento de Almuñécar | I93: Contrato de Obras de Mejora de protecciones y drenajes de varios caminos en el entorno del Río Seco, en el término municipal de Almuñécar, subvencionada por la Diputación Provincial de Granada `Subvención para reparación de daños producidos por temporal e inversiones de carácter preventivo. - Línea 1.` | J93: 105/2026 (GEST 8480 BIS/2026) | K93: Negociado sin publicidad | L93: 3 | N93: 0 | P93: 45233200 | Q93: Ver | R93: PCAP | S93: 46314 | T93: 46318.521
A94: En plazo | B94: 46335.999 | C94: 44811.5 | D94: 44811.5 | E94: Andalucía | F94: Huelva | G94: Cabezas Rubias | H94: Alcaldía del Ayuntamiento de Cabezas Rubias | I94: Contrato de Obras para La Intervención en los Espacios Libres de la Casa del Médico | J94: 2026/CON_02/000011 - 71/2026 | K94: Abierto simplificado | L94: 2 | N94: 0 | P94: 45112710 | Q94: Ver | R94: PCAP | S94: 46321 | T94: 46318.52
A95: Pendiente de adjudicación | B95: 46233.999 | C95: 216774.32 | D95: 216774.32 | E95: Comunitat Valenciana | F95: Valencia | G95: Ontinyent | H95: Alcaldia del Ayuntamiento de Ontinyent | I95: Contratación de las obras del "Proyecto de reforma de la iluminación y adecuación eléctrica de la pista de atletismo del Polideportivo Municipal de Ontinyent". | J95: 2910703T | K95: Abierto simplificado | L95: 4 | N95: 0 | P95: 45316100; 45310000 | Q95: Ver | R95: PCAP | S95: 46321 | T95: 46318.52
A96: En plazo | B96: 46338.999 | C96: 44187.31 | D96: 44187.31 | E96: Comunitat Valenciana | F96: Valencia | G96: Tavernes Blanques | H96: Alcaldía del Ayuntamiento de Tavernes Blanques | I96: Mejora de accesibilidad de los aseos púbicos de la biblioteca municipal de Tavernes Blanques | J96: OB-2026-4 | K96: Abierto simplificado | L96: 1.5 | N96: 0 | P96: 45000000; 45215500; 45111100 | Q96: Ver | R96: PCAP | S96: 46321 | T96: 46318.516
A97: En plazo | B97: 46338.999 | C97: 102350.31 | D97: 102350.31 | E97: Comunitat Valenciana | F97: Valencia | H97: Gerencia del Hospital Intermutual de Levante | I97: Obras de reforma, renovación e instalación de nuevos vestuarios en planta sótano de hospitalización del Hospital Intermutual de Levante | J97: HIL/2026/03/102 | K97: Abierto simplificado | L97: 1.5 | N97: 0.25 | P97: 45000000; 45400000 | Q97: Ver | R97: PCAP | S97: 46321 | T97: 46318.516
A98: Resuelta | B98: 46240.583 | C98: 57000 | D98: 68400 | E98: Comunitat Valenciana | F98: Valencia | H98: Gerencia umivale Activa, Mutua Colaboradora con la Seguridad Social número 3 | I98: Instalación de Placas fotovoltaicas para el centro de umivale Activa en Ontinyent (Llave en mano) | J98: OBR-26-0234-SOM | K98: Abierto | L98: 38 | N98: 0.4 | P98: 45261215; 45310000; 45259000 | Q98: Ver | R98: PCAP | S98: 46321 | T98: 46318.512
A99: Resuelta | B99: 46231.999 | C99: 230737.69 | D99: 230737.69 | E99: Andalucía | F99: Huelva | G99: Cartaya | H99: Alcaldía del Ayuntamiento de Cartaya | I99: Obras de reparación y/o restitución de las infraestructuras dañadas en las Calles Alto Buenavista y Escalerilla del Alto en Cartaya (Huelva), Expediente S-32/2026. | J99: 8264/2026 | K99: Abierto simplificado | L99: 6 | N99: 0.25 | P99: 45000000; 45233252 | Q99: Ver | R99: PCAP | S99: 46321 | T99: 46318.51
A100: En plazo | B100: 46339.542 | C100: 220533.97 | D100: 242587.36 | E100: Comunitat Valenciana | F100: Alicante | H100: Comité Ejecutivo de la Mancomunidad de los Canales del Taibilla | I100: Proyecto 02/26 para el amojonamiento de los Canales de Alicante desde el Sifón de Argüeda hasta la Elevación Nº2 de Crevillente (AC/Varios). | J100: O-02/26-02 | K100: Abierto simplificado | L100: 6 | N100: 0 | P100: 45259000 | Q100: Ver | R100: PCAP | S100: 46321 | T100: 46318.508
...
